Workbook
Name AggPlant100.T: '[1]BACOLOD RENTAL RATES'!#REF!
Name AggPlant100.T: '[1]BACOLOD RENTAL RATES'!#REF!
Name AggPlant100.T: '[1]BACOLOD RENTAL RATES'!#REF!
Name AggPlant100.T: '[1]BACOLOD RENTAL RATES'!#REF!
Name AggPlant100.T: '[1]BACOLOD RENTAL RATES'!#REF!
Name AggPlant100.T: '[1]BACOLOD RENTAL RATES'!#REF!
Name AggPlant100.T: '[1]BACOLOD RENTAL RATES'!#REF!
Name AggPlant100.T: '[1]BACOLOD RENTAL RATES'!#REF!
Name AggPlant100.T: '[1]BACOLOD RENTAL RATES'!#REF!
Name AshDist3000.T: '[1]BACOLOD RENTAL RATES'!#REF!
Name AshDist3000.T: '[1]BACOLOD RENTAL RATES'!#REF!
Name AshDist3000.T: '[1]BACOLOD RENTAL RATES'!#REF!
Name AshDist3000.T: '[1]BACOLOD RENTAL RATES'!#REF!
Name AshDist3000.T: '[1]BACOLOD RENTAL RATES'!#REF!
Name AshDist3000.T: '[1]BACOLOD RENTAL RATES'!#REF!
Name AshDist3000.T: '[1]BACOLOD RENTAL RATES'!#REF!
Name AshDist3000.T: '[1]BACOLOD RENTAL RATES'!#REF!
Name AshPaver88.T: '[1]BACOLOD RENTAL RATES'!#REF!
Name AshPaver88.T: '[1]BACOLOD RENTAL RATES'!#REF!
Name AshPaver88.T: '[1]BACOLOD RENTAL RATES'!#REF!
Name AshPaver88.T: '[1]BACOLOD RENTAL RATES'!#REF!
Name AshPaver88.T: '[1]BACOLOD RENTAL RATES'!#REF!
Name AshPaver88.T: '[1]BACOLOD RENTAL RATES'!#REF!
Name AshPaver88.T: '[1]BACOLOD RENTAL RATES'!#REF!
Name AshPlant100.T: '[1]BACOLOD RENTAL RATES'!#REF!
Name AshPlant100.T: '[1]BACOLOD RENTAL RATES'!#REF!
Name AshPlant100.T: '[1]BACOLOD RENTAL RATES'!#REF!
Name AshPlant100.T: '[1]BACOLOD RENTAL RATES'!#REF!
Name AshPlant100.T: '[1]BACOLOD RENTAL RATES'!#REF!
Name AshPlant100.T: '[1]BACOLOD RENTAL RATES'!#REF!
Name AshPlant100.T: '[1]BACOLOD RENTAL RATES'!#REF!
Name AshPlant30.T: '[1]BACOLOD RENTAL RATES'!#REF!
Name AshPlant30.T: '[1]BACOLOD RENTAL RATES'!#REF!
Name AshPlant30.T: '[1]BACOLOD RENTAL RATES'!#REF!
Name AshPlant30.T: '[1]BACOLOD RENTAL RATES'!#REF!
Name AshPlant30.T: '[1]BACOLOD RENTAL RATES'!#REF!
Name AshPlant30.T: '[1]BACOLOD RENTAL RATES'!#REF!
Name AshPlant30.T: '[1]BACOLOD RENTAL RATES'!#REF!
Name AshPlant60.T: '[1]BACOLOD RENTAL RATES'!#REF!
Name AshPlant60.T: '[1]BACOLOD RENTAL RATES'!#REF!
Name AshPlant60.T: '[1]BACOLOD RENTAL RATES'!#REF!
Name AshPlant60.T: '[1]BACOLOD RENTAL RATES'!#REF!
Name AshPlant60.T: '[1]BACOLOD RENTAL RATES'!#REF!
Name AshPlant60.T: '[1]BACOLOD RENTAL RATES'!#REF!
Name AshPlant60.T: '[1]BACOLOD RENTAL RATES'!#REF!
Name Backhoe.63m3.T: '[1]BACOLOD RENTAL RATES'!#REF!
Name Backhoe.63m3.T: '[1]BACOLOD RENTAL RATES'!#REF!
Name Backhoe.63m3.T: '[1]BACOLOD RENTAL RATES'!#REF!
Name Backhoe.63m3.T: '[1]BACOLOD RENTAL RATES'!#REF!
Name Backhoe.63m3.T: '[1]BACOLOD RENTAL RATES'!#REF!
Name Backhoe.63m3.T: '[1]BACOLOD RENTAL RATES'!#REF!
Name Backhoe.63m3.T: '[1]BACOLOD RENTAL RATES'!#REF!
Name Backhoe.76m3.T: '[1]BACOLOD RENTAL RATES'!#REF!
Name Backhoe.76m3.T: '[1]BACOLOD RENTAL RATES'!#REF!
Name Backhoe.76m3.T: '[1]BACOLOD RENTAL RATES'!#REF!
Name Backhoe.76m3.T: '[1]BACOLOD RENTAL RATES'!#REF!
Name Backhoe.76m3.T: '[1]BACOLOD RENTAL RATES'!#REF!
Name Backhoe.76m3.T: '[1]BACOLOD RENTAL RATES'!#REF!
Name Backhoe.76m3.T: '[1]BACOLOD RENTAL RATES'!#REF!
Name Backhoe1.18m3.T: '[1]BACOLOD RENTAL RATES'!#REF!

Sheet time elapse
A2: Republic of the Philippines
A3: PROVINCE OF CAGAYAN
A4: Capitol Hills, Tuguegarao City
A5: PROVINCIAL ENGINEER'S OFFICE
J6: NTP: | K6: 44356
A7: STATEMENT OF TIME ELAPSED AND WORK ACCOMPLISHED
B9: 45117 | F9: * | G9: To be Filled up | I9: Note:
A10: Project name | C10: : | D10: =SWA!B4 -> Construction of Abra-Baracaoit Flat Slab Bridge | F10: * | G10: To be Filled up | I10: Just fill up those items with red boxes beside
F11: * | G11: To be Filled up
A12: Location | C12: : | D12: Gattaran, Cagayan | F12: * | G12: To be Filled up | J12: =D16-D15 -> 586
A13: Contract Amount | C13: : | D13: =SWA!G43 -> 19963541 | F13: *
A14: Contractor | C14: : | D14: FOUR R CONSTRUCTION | F14: * | G14: To be Filled up | I14: =+D24-D17 -> 267 | J14: Days
A15: 1. | B15: Period Covered: | C15: : | D15: =D18+10-1 -> 44531 | E15: to | G15: Don't Fill Up | I15: =IF(D24>D17,"Beyond the Contract Duration!!!!!!!","Within Contract") -> Beyond the Contract Duration!!!!!!!
D16: =+B9 -> 45117 | G16: Don't Fill Up
A17: 2. | B17: Contract Duration: | C17: : | D17: 320 | F17: * | G17: To be Filled up
A18: 3. | B18: Notice to Proceed | C18: : | D18: 44522 | G18: Don't Fill Up | J18: =+D15 -> 44531 | K18: 42583 | L18: =+K18-J18 -> -1948
A19: 5. | B19: Expiry Date | C19: : | D19: =+D15+D17-1 -> 44850 | G19: Don't Fill Up | K19: 50.72 | L19: 19
A20: 6. | B20: Approved Time Extension | C20: : | D20: =15+25+18+20+24+30 -> 132 | F20: * | G20: To be Filled up | L20: =+L18-L19 -> -1967
A21: 12 | B21: Approved Time Suspension | C21: : | D21: 135 | F21: * | G21: To be Filled up | J21: 42602 | K21: 42633 | L21: =+K21-J21 -> 31
A22: 13 | B22: Revised Contract Duration | C22: : | D22: =+SUM(D20:D21)+D17 -> 587 | G22: Don't Fill Up | M22: =+D24-D22 -> 0
A23: 14. | B23: Revised Expiry Date due to Suspension | C23: : | D23: =+D19+D21+SUM(D20:D20) -> 45117 | G23: Don't Fill Up
A24: 15. | B24: Total Calendar days Elapsed to Date | C24: : | D24: =+D16-D15+1 -> 587 | G24: Don't Fill Up
A25: 16 | B25: Percentage Of work accomplished-Actual | C25: : | D25: =SWA!L43 -> 0.57069 | F25: * | G25: To be Filled up
A26: 17. | B26: Percentage Of work accomplished-Planned | C26: : | D26: 1 | G26: Don't Fill Up | J26: =(((SIN((((180*((D24-D21))/D22)-90)*(3.14159265358979/180)))+1)*50)/100) -> 0.87507323
A27: 18 | B27: Slippage | C27: : | D27: =D25-D26 -> -0.42931 | G27: Don't Fill Up
A28: 19. | B28: Remarks | C28: : | F28: * | G28: To be Filled up | J28: =+D25-100% -> -0.42931
J29: =100-9.55 -> 90.45
M30: =100-69.39 -> 30.61
A31: Submitted by: | J31: 42200 | K31: =+J31-D15 -> -2331
K33: =649-120 -> 529
B34: MA. VICTORIA E. REYES
B35: Engineer II
K38: 1283860.6
J39: Liquidation Damages: | K39: =-1*(((K38*0.01*D27))/10)*(D24-D17) -> 147163.51 | M39: =((((1/100)*(D27*D13))*-1)/10)*(D24-D22) -> 0
J46: 42460
J47: =180+105 -> 285
J49: =+J46+J47 -> 42745

Sheet time elapse (2)
A2: Republic of the Philippines
A3: PROVINCE OF CAGAYAN
A4: Capitol Hills, Tuguegarao City
A5: PROVINCIAL ENGINEER'S OFFICE
J6: NTP: | K6: 44356
A7: STATEMENT OF TIME ELAPSED AND WORK ACCOMPLISHED
B9: =TODAY() -> 46183 | F9: * | G9: To be Filled up | I9: Note:
A10: Project name | C10: : | D10: =SWA!B4 -> Construction of Abra-Baracaoit Flat Slab Bridge | F10: * | G10: To be Filled up | I10: Just fill up those items with red boxes beside
F11: * | G11: To be Filled up
A12: Location | C12: : | D12: Gattaran, Cagayan | F12: * | G12: To be Filled up | J12: =D16-D15 -> 1652
A13: Contract Amount | C13: : | D13: =SWA!G43 -> 19963541 | F13: *
A14: Contractor | C14: : | D14: FOUR R CONSTRUCTION | F14: * | G14: To be Filled up | I14: =+D24-D17 -> 1333 | J14: Days
A15: 1. | B15: Period Covered: | C15: : | D15: =D18+10-1 -> 44531 | E15: to | G15: Don't Fill Up | I15: =IF(D24>D17,"Beyond the Contract Duration!!!!!!!","Within Contract") -> Beyond the Contract Duration!!!!!!!
D16: =+B9 -> 46183 | G16: Don't Fill Up
A17: 2. | B17: Contract Duration: | C17: : | D17: 320 | F17: * | G17: To be Filled up
A18: 3. | B18: Notice to Proceed | C18: : | D18: 44522 | G18: Don't Fill Up | J18: =+D15 -> 44531 | K18: 42583 | L18: =+K18-J18 -> -1948
A19: 5. | B19: Expiry Date | C19: : | D19: =+D15+D17-1 -> 44850 | G19: Don't Fill Up | K19: 50.72 | L19: 19
A20: 6. | B20: Approved Time Extension | C20: : | D20: =15+25+18+20+24+30 -> 132 | F20: * | G20: To be Filled up | L20: =+L18-L19 -> -1967
A21: 12 | B21: Approved Time Suspension | C21: : | D21: 135 | F21: * | G21: To be Filled up | J21: 42602 | K21: 42633 | L21: =+K21-J21 -> 31
A22: 13 | B22: Revised Contract Duration | C22: : | D22: =+SUM(D20:D21)+D17 -> 587 | G22: Don't Fill Up | M22: =+D24-D22 -> 1066
A23: 14. | B23: Revised Expiry Date due to Suspension | C23: : | D23: =+D19+D21+SUM(D20:D20) -> 45117 | G23: Don't Fill Up
A24: 15. | B24: Total Calendar days Elapsed to Date | C24: : | D24: =+D16-D15+1 -> 1653 | G24: Don't Fill Up
A25: 16 | B25: Percentage Of work accomplished-Actual | C25: : | D25: =#REF! -> #REF! | F25: * | G25: To be Filled up
A26: 17. | B26: Percentage Of work accomplished-Planned | C26: : | D26: 1 | G26: Don't Fill Up | J26: =(((SIN((((180*((D24-D21))/D22)-90)*(3.14159265358979/180)))+1)*50)/100) -> 0.63349741
A27: 18 | B27: Slippage | C27: : | D27: =D25-D26 -> #REF! | G27: Don't Fill Up
A28: 19. | B28: Remarks | C28: : | F28: * | G28: To be Filled up | J28: =+D25-100% -> #REF!
J29: =100-9.55 -> 90.45
M30: =100-69.39 -> 30.61
A31: Submitted by: | J31: 42200 | K31: =+J31-D15 -> -2331
K33: =649-120 -> 529
B34: MA. VICTORIA E. REYES
B35: Engineer II
K38: 1283860.6
J39: Liquidation Damages: | K39: =-1*(((K38*0.01*D27))/10)*(D24-D17) -> #REF! | M39: =((((1/100)*(D27*D13))*-1)/10)*(D24-D22) -> #REF!
J46: 42460
J47: =180+105 -> 285
J49: =+J46+J47 -> 42745

Sheet stewa(EXPIRY)
A2: Republic of the Philippines
A3: PROVINCE OF CAGAYAN
A4: Capitol Hills, Tuguegarao City
A5: PROVINCIAL ENGINEER'S OFFICE
H6: JUST FILL IN ON BLUE CELL!!! | M6: LEGEND:
A7: STATEMENT OF TIME ELAPSED AND WORK ACCOMPLISHED | M7: single | N7: WITHOUT REVISION
M8: in a relationship | N8: WITH REVISION
B9: =I9 -> 45117 | H9: To be Filled In | I9: 45117 | M9: complicated | N9: ON THE EXPIRY DATE WITHOUT REVISION
M10: married | N10: ON THE EXPIRY DATE WITH REVISION
M11: separated | N11: ON THE COMPLETION DATE WITHOUT REVISION
A12: Project Name | C12: : | D12: =I12 -> #REF! | H12: To be Filled In | I12: =#REF! -> #REF! | J12: Project Name | M12: divorced | N12: ON THE COMPLETION DATE WITH REVISION
A13: Location | C13: : | D13: =I13 -> #REF! | H13: To be Filled In | I13: =#REF! -> #REF! | J13: Location | M13: LDR_1 | N13: WITHOUT REVISION
A14: Contract Amount | C14: : | D14: =I14 -> #REF! | H14: To be Filled In | I14: =#REF! -> #REF! | J14: Contract Amount | M14: LDR_2 | N14: WITH REVISION
A15: Contractor | C15: : | D15: =I15 -> FOUR R CONSTRUCTION | H15: To be Filled In | I15: FOUR R CONSTRUCTION | J15: Contractor
A17: 1. | B17: Period Covered: | C17: : | D17: =D20+10 -> 44532 | E17: to
D18: =+B9 -> 45117
A19: 2. | B19: Contract Duration | C19: : | D19: =I19 -> 320 | H19: To be Filled In | I19: 320 | J19: Contract Duration
A20: 3. | B20: Date of Receipt of Notice to Proceed | C20: : | D20: =I20 -> 44522 | H20: To be Filled In | I20: 44522 | J20: Date of Receipt of Notice to Proceed
A21: 4. | B21: Expiry Date | C21: : | D21: =+D17+D19-2 -> 44850
A22: 5. | B22: Approved Time Extension | C22: : | D22: =D23+I22 -> 267 | H22: To be Filled In | I22: 132 | J22: Approved Time Extension
A23: 6. | B23: Approved Time Suspension | C23: : | D23: =I23 -> 135 | H23: To be Filled In | I23: 135 | J23: Approved Time Suspension
A24: 7. | B24: Total Time Extension | D24: =IF(I24>0,I24,0) -> 267 | H24: Don't Fill In | I24: =D22 -> 267 | J24: Total Time Extension
A25: 8. | B25: Revised Contract Duration | C25: : | D25: =IF(I24>0,I25,0) -> 586 | H25: Don't Fill In | I25: =IF(D22>0,D22+I19,0)-1 -> 586 | J25: Revised Contract Duration
A26: 9. | B26: Revised Expiry Date | C26: : | D26: =IF(I24>0,D21+D24,"") -> 45117
A27: 10. | B27: Total Calendar days Elapsed to Date | C27: : | D27: =+D18-D17+1 -> 586
A28: 11. | B28: Percentage of work accomplished - Actual | C28: : | D28: =I28 -> 0.57069 | I28: 0.57069 | J28: (FROM SWA)
A29: 12. | B29: Percentage of work accomplished -Planned | C29: : | D29: =I33 -> 1 | H29: Don't Fill In | I29: =(((SIN((((180*((D27))/D19)-90)*(3.14159265358979/180)))+1)*50)/100) -> 0.068632807 | J29: W/ FORMULA - Planned (WITHOUT time extension)
A30: 13. | B30: Slippage | C30: : | D30: =D28-D29 -> -0.42931 | H30: Don't Fill In | I30: =IF(I25>0,(((SIN((((180*((D27))/D25)-90)*(3.14159265358979/180)))+1)*50)/100),"") -> 1 | J30: W/ FORMULA - Planned (WITH time extension)
A31: 14. | B31: Remarks | C31: :
H32: Don't Fill In | I32: =D27/D19 -> 1.83125 | J32: LINEAR - Planned (WITHOUT time extension)
H33: Don't Fill In | I33: 1 | J33: LINEAR - Planned (WITH time extension)
B35: Submitted by: | D35: Noted by: | H35: F | I35: WRITE "F" - OPT TO USE FORMULA
I36: WRITE "L" - OPT TO USE LINEAR
B38: MA. VICTORIA E. REYES | D38: ARNOLD L. MANUEL
B39: Engineer II | D39: OIC Chief - Construction Division

Sheet SWA
B1: STATEMENT OF WORK ACCOMPLISHMENT
B2: As of July 10, 2023 (expiry date)
A4: Project Title: | B4: Construction of Abra-Baracaoit Flat Slab Bridge
A5: Location: | B5: =swa_BC!B5 -> Gonzaga, Cagayan
A7: ITEM | B7: DESCRIPTION OF WORK | D7: PROGRAMMED | F7: UNIT | G7: CONTRACT | H7: WEIGHT | I7: ACCOMPLISHMENT | L7: WEIGHT | M7: REMARKS/
A8: NO. | D8: QUANTITY | F8: PRICE | G8: AMOUNT | H8: % | I8: PREVIOUS | J8: THIS PERIOD | K8: TO DATE | L8: % | M8: STATUS | N8: =#REF!/6.1 -> #REF! | O8: =N8*2 -> #REF! | R8: less
D9: ORIGINAL | N9: 650 | O9: 1320 | P9: =O9/2 -> 660 | Q9: contract | S9: adj. amount
A10: PART A | B10: FACILITIES FOR ENGINEERS
A11: A.1.1 (8) | B11: Provision of Field Office for the Engineer (Rental Basis) | D11: 10.67 | E11: mo | F11: 5775 | G11: =ROUND(F11*D11,2) -> 61619.25 | H11: =ROUND((G11/$G$43),5) -> 0.00309 | I11: 49295.4 | J11: =K11-I11 -> 0 | K11: =G11*0.8 -> 49295.4 | L11: =ROUND(K11/G43,5) -> 0.00247 | M11: =IF(L11=H11,"COMPLETED","On-going") -> On-going | N11: =4.9*F11 -> 28297.5
A12: PART B | B12: OTHER GENERAL REQUIREMENTS
A13: B.5 | B13: Billboards and Signages | D13: 2 | E13: each | F13: 11655 | G13: =ROUND(F13*D13,2) -> 23310 | H13: =ROUND((G13/$G$43),5) -> 0.00117 | I13: 11655 | J13: =K13-I13 -> 0 | K13: =F13*1 -> 11655 | L13: =ROUND(K13/G43,5) -> 0.00058 | M13: =IF(L13=H13,"COMPLETED","On-going") -> On-going
A14: B.7 | B14: Construction Safety and Health Program | D14: all | E14: l.s | F14: 49665 | G14: =F14 -> 49665 | H14: =ROUND((G14/$G$43),5) -> 0.00249 | I14: 39732 | J14: =K14-I14 -> 0 | K14: =G14*0.8 -> 39732 | L14: =ROUND(K14/G43,5) -> 0.00199 | M14: =IF(L14=H14,"COMPLETED","On-going") -> On-going | N14: =0.5*F14 -> 24832.5
A15: B.9 | B15: Mobilization/ Demobilization | D15: all | E15: l.s | F15: 175000 | G15: =F15 -> 175000 | H15: =ROUND((G15/$G$43),5) -> 0.00877 | I15: 87500 | J15: =K15-I15 -> 0 | K15: =0.5*G15 -> 87500 | L15: =ROUND(K15/G43,5) -> 0.00438 | M15: =IF(L15=H15,"COMPLETED","On-going") -> On-going
A16: I | B16: ROAD
A17: PART C | B17: EARTHWORKS
A18: 102(2) | B18: Roadway Excavation (Surplus Common Materials) | D18: 1871.15 | E18: cu.m | F18: 142.59 | G18: =ROUND(F18*D18,2) -> 266807.28 | H18: =ROUND((G18/$G$43),5) -> 0.01336 | I18: 186765.1 | J18: =K18-I18 -> 0 | K18: =ROUND(0.7*G18,2) -> 186765.1 | L18: =ROUND(K18/G43,5) -> 0.00936 | M18: =IF(L18=H18,"COMPLETED","On-going") -> On-going
A19: 104(1)a | B19: Embankment | D19: 743.28 | E19: cu.m | F19: 111.2 | G19: =ROUND(F19*D19,2) -> 82652.74 | H19: =ROUND((G19/$G$43),5) -> 0.00414 | I19: 57856.92 | J19: =K19-I19 -> 0 | K19: =ROUND(0.7*G19,2) -> 57856.92 | L19: =ROUND(K19/G43,5) -> 0.0029 | M19: =IF(L19=H19,"COMPLETED","On-going") -> On-going | N19: =371.64*F19 -> 41326.368
A20: 105(1) | B20: Sub-Grade Preparation (Common Materials) | D20: 2481.5 | E20: sq.m | F20: 17.44 | G20: =ROUND(F20*D20,2) -> 43277.36 | H20: =ROUND((G20/$G$43),5) -> 0.00217 | I20: 30294.15 | J20: =K20-I20 -> 0 | K20: =ROUND(G20*0.7,2) -> 30294.15 | L20: =ROUND(K20/G43,5) -> 0.00152 | M20: =IF(L20=H20,"COMPLETED","On-going") -> On-going | N20: =1240.75*F20 -> 21638.68
A21: PART D | B21: SUBBASE COURSE
A22: 200(1) | B22: Aggregate Sub-base Course | D22: 760.33 | E22: cu.m | F22: 684.79 | G22: =ROUND(F22*D22,2) -> 520666.38 | H22: =ROUND((G22/$G$43),5) -> 0.02608 | I22: 225764.99 | J22: =K22-I22 -> 0 | K22: =ROUND((177.25*0.2*5*F22)+(177.25*0.43*F22*2),2) -> 225764.99 | L22: =ROUND(K22/G43,5) -> 0.01131 | M22: =IF(L22=H22,"COMPLETED","On-going") -> On-going | N22: =380.165*F22 -> 260333.19 | O22: 0.8 | Q22: =D22*F22 -> 520666.38 | R22: =ROUND($R$9*Q22,2) -> 0 | S22: =Q22-R22 -> 520666.38 | T22: 40384.71
A23: PART E | B23: SURFACE COURSE | O23: 0.8 | Q23: =D23*F23 -> 0 | R23: =ROUND($R$9*Q23,2) -> 0 | S23: =Q23-R23 -> 0 | T23: 23203.8
A24: =swa_BC!A12 -> 0 | B24: =swa_BC!B12 -> Mobilization/ Demobilization | D24: 1772.5 | E24: =swa_BC!E12 -> sq.m | F24: 1248.35 | G24: =ROUND(F24*D24,2) -> 2212700.4 | H24: =ROUND((G24/$G$43),5) -> 0.11084 | I24: 1106350.2 | J24: =K24-I24 -> 0 | K24: =K24-I24 -> 0 | L24: =ROUND(K24/G43,5) -> 0.07793 | M24: =IF(L24=H24,"COMPLETED","On-going") -> On-going | N24: =(443.125+180)*F24*2 -> 1555756.2 | O24: =443.125/2.5 -> 177.25 | Q24: =D24*F24 -> 2212700.4 | R24: =ROUND($R$9*Q24,2) -> 0 | S24: =Q24-R24 -> 2212700.4 | T24: 61058.41
A25: II | B25: CONSTRUCTION OF BRIDGE (FLAT SLAB) | Q25: =D25*F25 -> 0 | R25: =ROUND($R$9*Q25,2) -> 0 | S25: =Q25-R25 -> 0 | T25: 1127300.6
A26: A | B26: EARTHWORKS | Q26: =D26*F26 -> 0 | R26: =ROUND($R$9*Q26,2) -> 0 | S26: =Q26-R26 -> 0 | T26: 3199178.4
A27: 103(1)a | B27: Structure Excavation | D27: 83.28 | E27: =swa_BC!E15 -> cu.m | F27: 127.85 | G27: =ROUND(F27*D27,2) -> 10647.35 | H27: =ROUND((G27/$G$43),5) -> 0.00053 | L27: =ROUND(K27/G43,5) -> 0 | M27: not yet started | N27: =G27 -> 10647.35
A28: B.18 | B28: Craneway | D28: all | E28: l.s | F28: 3120000 | G28: =F28 -> 3120000 | H28: =ROUND((G28/$G$43),5) -> 0.15628 | I28: 2340000 | J28: =K28-I28 -> 0 | K28: =0.75*G28 -> 2340000 | L28: =ROUND(K28/G43,5) -> 0.11721 | M28: =IF(L28=H28,"COMPLETED","On-going") -> On-going | N28: =G28 -> 3120000
A29: B | B29: SUB-STRUCTURE
A30: 404(4)a | B30: Precast Concrete Piles, Furnished | D30: 784 | E30: ln.m | F30: 5449.5 | G30: =ROUND(F30*D30,2) -> 4272408 | H30: =ROUND((G30/$G$43),5) -> 0.21401 | I30: 3269700 | J30: =K30-I30 -> 0 | K30: =N30 -> 3269700 | L30: =ROUND(K30/G43,5) -> 0.16378 | M30: =IF(L30=H30,"COMPLETED","On-going") -> On-going | N30: =600*F30 -> 3269700 | O30: =50*12 -> 600
A31: 400(14) | B31: Precast Concrete Piles, Driven | D31: 539 | E31: ln.m | F31: 2106.23 | G31: =ROUND(F31*D31,2) -> 1135258 | H31: =ROUND((G31/$G$43),5) -> 0.05687 | I31: 631869 | J31: =K31-I31 -> 0 | K31: =N31 -> 631869 | L31: =ROUND(K31/G43,5) -> 0.03165 | M31: =IF(L31=H31,"COMPLETED","On-going") -> On-going | N31: =25*12*F31 -> 631869
A32: 400(16)a | B32: Test Piles, furnished and Driven (400mmx400mm) | D32: 16 | E32: ln.m | F32: 7308 | G32: =ROUND(F32*D32,2) -> 116928 | H32: =ROUND((G32/$G$43),5) -> 0.00586 | I32: 109620 | J32: =K32-I32 -> 0 | K32: =F32*15 -> 109620 | L32: =ROUND(K32/G43,5) -> 0.00549 | M32: =IF(L32=H32,"COMPLETED","On-going") -> On-going | N32: =G32 -> 116928 | Q32: =D32*F32 -> 116928 | R32: =ROUND($R$9*Q32,2) -> 0 | S32: =Q32-R32 -> 116928 | T32: 32303.68
A33: C | B33: SUPERSTRUCTURE | Q33: =D33*F33 -> 0 | R33: =ROUND($R$9*Q33,2) -> 0 | S33: =Q33-R33 -> 0 | T33: 23203.8
A34: 404(1)b | B34: Reinforcing Steel Bars | D34: 35236.81 | E34: kg. | F34: 90.34 | G34: =ROUND(F34*D34,2) -> 3183293.4 | H34: =ROUND((G34/$G$43),5) -> 0.15946 | I34: 1206153.9 | J34: =K34-I34 -> 257063.17 | K34: =N34 -> 1463217.1 | L34: =ROUND(K34/G43,5) -> 0.07329 | M34: =IF(L34=H34,"COMPLETED","On-going") -> On-going | N34: =Q34*4*F34 -> 1463217.1 | O34: 4740.195 | P34: 691 | Q34: =O34-P34 -> 4049.195 | R34: =ROUND($R$9*Q34,2) -> 0 | S34: =Q34-R34 -> 4049.195 | T34: 61058.41
A35: 405(1)b | B35: Structural Concrete Class A-Bridge Superstructure 27 Mpa | D35: 250.79 | E35: cu.m | F35: 10432.84 | G35: =ROUND(F35*D35,2) -> 2616451.9 | H35: =ROUND((G35/$G$43),5) -> 0.13106 | I35: =ROUND(735723.88,2) -> 735723.88 | J35: =K35-I35 -> 598406.83 | K35: =N35 -> 1334130.7 | L35: =ROUND(K35/G43,5) -> 0.06683 | M35: =IF(L35=H35,"COMPLETED","On-going") -> On-going | N35: =((O35*4)+(4.67*5))*F35 -> 1334130.7 | O35: =21.462+4.67 -> 26.132
A36: D | B36: SLOPE PROTECTION | O36: 4.672
A37: 404(1)a | B37: Reinforcing Steel Bars | D37: 7375.11 | E37: kg. | F37: 88.98 | G37: =ROUND(F37*D37,2) -> 656237.29 | H37: =ROUND((G37/$G$43),5) -> 0.03287 | K37: =J37-I37 -> 0 | L37: =ROUND(K37/G43,5) -> 0 | M37: not yet started
A38: 405(1)a | B38: Structural Concrete Class A 20.7 Mpa | D38: 136.68 | E38: cu.m | F38: 6860.58 | G38: =ROUND(F38*D38,2) -> 937704.07 | H38: =ROUND((G38/$G$43),5) -> 0.04697 | K38: =J38-I38 -> 0 | L38: =ROUND(K38/G43,5) -> 0 | M38: not yet started
A39: E | B39: BRIDGE APPROACH | Q39: =D39*F39 -> 0 | R39: =ROUND($R$9*Q39,2) -> 0 | S39: =Q39-R39 -> 0 | T39: 1127300.6
A40: 404(1)a | B40: Reinforcing Steel Bars | D40: 3194.34 | E40: kg. | F40: 100.33 | G40: =ROUND(F40*D40,2) -> 320488.13 | H40: =ROUND((G40/$G$43),5) -> 0.01605 | K40: =J40-I40 -> 0 | L40: =ROUND(K40/G43,5) -> 0 | M40: not yet started | N40: 11 | Q40: =D40*F40 -> 320488.13 | R40: =ROUND($R$9*Q40,2) -> 0 | S40: =Q40-R40 -> 320488.13 | T40: 3199178.4
A41: 405(1)a | B41: Structural Concrete Class A 20.7 Mpa | D41: 18.71 | E41: cu.m | F41: 8467.46 | G41: =ROUND(F41*D41,2) -> 158426.18 | H41: =ROUND((G41/$G$43),5) -> 0.00794 | K41: =J41-I41 -> 0 | L41: =ROUND(K41/G43,5) -> 0 | M41: not yet started
A43: T O T A L S | G43: =SUM(G11:G42) -> 19963541 | H43: =SUM(H11:H41) -> 1.00001 | I43: 9625182 | J43: =SUM(J11:J42) -> 855470 | K43: =SUM(K11:K42) -> 11393157 | L43: =SUM(L11:L41) -> 0.57069 | Q43: =SUM(Q22:Q40) -> 3174832.1 | R43: =SUM(R22:R40) -> 0 | S43: =SUM(S22:S40) -> 3174832.1 | T43: =SUM(T22:T40) -> 8894170.6
Q44: =ROUND(Q43*R9,2) -> 0
Q45: =Q43-Q44 -> 3174832.1
F46: % THIS ACCOMPLISHMENT | I46: =L43 -> 0.57069 | Q46: =Q44-Q45 -> -3174832.1
F47: TOTAL PROJECT COST | I47: =G43 -> 19963541
F48: TOTAL THIS ACCOMPLISHMENT | I48: =J43 -> 855470
E49: Less: | F49: MOBILIZATION
F50: TOTAL THIS VOUCHER | I50: =SUM(J43-I49) -> 855470
A52: Prepared by: | C52: Checked by: | G52: Recommending Approval: | K52: Approved:
A56: MA. VICTORIA E. REYES | C56: ARNOLD L. MANUEL | G56: KINGSTON JAMES S. DELA CRUZ | K56: MANUEL N. MAMBA, M.D.
A57: Engineer II | C57: OIC- Chief of Construction Division | G57: Provincial Engineer | K57: Governor
B59: =B1 -> STATEMENT OF WORK ACCOMPLISHMENT
B60: As of _____________________, 2020
A62: A. | B62: ='[2]SWA(abd)'!B12 -> CONCRETING OF FARM TO MARKET ROAD ZIMINILA
B63: ='[2]SWA(abd)'!B13 -> CAMALANIUGAN, CAGAYAN
A65: ITEM | B65: DESCRIPTION OF WORK | D65: PROGRAMMED | F65: UNIT | G65: CONTRACT | H65: WEIGHT | I65: ACCOMPLISHMENT | L65: WEIGHT | M65: REMARKS/
A66: NO. | D66: QUANTITY | F66: PRICE | G66: AMOUNT | H66: % | I66: PREVIOUS | J66: THIS PERIOD | K66: TO DATE | L66: % | M66: STATUS
D67: ORIGINAL | R67: 0.16
A68: ='[2]SWA(abd)'!A17 -> 105(1) | B68: ='[2]SWA(abd)'!B17:C17 -> Sub Grade Preparation | D68: ='[2]SWA(abd)'!D17 -> 1075.8 | E68: ='[2]SWA(abd)'!E17 -> sq.m. | F68: ='[2]SWA(abd)'!F17 -> 102.17 | G68: ='[2]SWA(abd)'!G17 -> 109364.91 | H68: =(G68/$G$75)*100 -> 10.022838 | K68: =I68+J68 -> 0 | L68: =ROUND(K68/#REF!,4) -> #REF! | M68: on-going | Q68: =D68*F68 -> 109914.49 | R68: =Q68*$R$67 -> 17586.318 | S68: =Q68-R68 -> 92328.168
A69: ='[2]SWA(abd)'!A18 -> 200(1) | B69: ='[2]SWA(abd)'!B18:C18 -> Aggregate Sub Base Coarse | D69: ='[2]SWA(abd)'!D18 -> 173.25 | E69: ='[2]SWA(abd)'!E18 -> sq.m. | F69: 804.58 | G69: ='[2]SWA(abd)'!G18 -> 223636.89 | H69: =(G69/$G$75)*100 -> 20.495388 | K69: =I69+J69 -> 0 | L69: =ROUND(K69/$G$75,4) -> 0 | M69: on-going | Q69: =D69*F69 -> 139393.49 | R69: =Q69*$R$67 -> 22302.958 | S69: =Q69-R69 -> 117090.53
A70: ='[2]SWA(abd)'!A19 -> 311(1)C | B70: ='[2]SWA(abd)'!B19:C19 -> PCCP | D70: ='[2]SWA(abd)'!D19 -> 660 | E70: ='[2]SWA(abd)'!E19 -> sq.m. | F70: 72.96 | G70: ='[2]SWA(abd)'!G19 -> 672973.03 | H70: =(G70/$G$75)*100 -> 61.675171 | K70: =I70+J70 -> 0 | L70: =ROUND(K70/$G$75,4) -> 0 | M70: on-going | O70: =0.2*#REF! -> #REF! | P70: =0.95*#REF! -> #REF! | Q70: =D70*F70 -> 48153.6 | R70: =Q70*$R$67 -> 7704.576 | S70: =Q70-R70 -> 40449.024
A71: ='[2]SWA(abd)'!A20 -> B.9 | B71: ='[2]SWA(abd)'!B20:C20 -> Mobilization/ Demobilization | D71: ='[2]SWA(abd)'!D20 -> 1 | E71: ='[2]SWA(abd)'!E20 -> l/s | F71: 128.93 | G71: ='[2]SWA(abd)'!G20 -> 25951.88 | H71: =(G71/$G$75)*100 -> 2.3783815 | K71: =I71+J71 -> 0 | L71: =ROUND(K71/$G$75,4) -> 0 | M71: on-going | O71: 604.87 | P71: =0.95*#REF! -> #REF! | Q71: =D71*F71 -> 128.93 | R71: =Q71*$R$67 -> 20.6288 | S71: =Q71-R71 -> 108.3012
A72: ='[2]SWA(abd)'!A21 -> B.5 | B72: ='[2]SWA(abd)'!B21:C21 -> Billboards and Signages | D72: ='[2]SWA(abd)'!D21 -> 2 | E72: ='[2]SWA(abd)'!E21 -> each | F72: 18.37 | G72: ='[2]SWA(abd)'!G21 -> 10196.76 | H72: =(G72/$G$75)*100 -> 0.93449052 | K72: =I72+J72 -> 0 | L72: =ROUND(K72/$G$75,4) -> 0 | M72: on-going | O72: =0.2*#REF! -> #REF! | P72: =0.95*#REF! -> #REF! | Q72: =D72*F72 -> 36.74 | R72: =Q72*$R$67 -> 5.8784 | S72: =Q72-R72 -> 30.8616
A73: ='[2]SWA(abd)'!A22 -> B.7 | B73: ='[2]SWA(abd)'!B22:C22 -> Occupational Health and Safety | D73: ='[2]SWA(abd)'!D22 -> 1 | E73: ='[2]SWA(abd)'!E22 -> l/s | F73: 1208.89 | G73: ='[2]SWA(abd)'!G22 -> 28041.09 | H73: =(G73/$G$75)*100 -> 2.5698489 | K73: =I73+J73 -> 0 | L73: =ROUND(K73/$G$75,4) -> 0 | M73: on-going | O73: =0.2*#REF! -> #REF! | P73: =0.9*#REF! -> #REF! | Q73: =D73*F73 -> 1208.89 | R73: =Q73*$R$67 -> 193.4224 | S73: =Q73-R73 -> 1015.4676
A74: ='[2]SWA(abd)'!A23 -> A.1.1(8a) | B74: ='[2]SWA(abd)'!B23:C23 -> Provisions of Field Office for the Engineer | D74: ='[2]SWA(abd)'!D23 -> 1.83 | E74: ='[2]SWA(abd)'!E23 -> mos | F74: 1291.19 | G74: ='[2]SWA(abd)'!G23 -> 20992.58 | H74: =(G74/$G$75)*100 -> 1.9238824 | K74: =I74+J74 -> 0 | L74: =ROUND(K74/$G$75,4) -> 0 | M74: on-going | O74: =350*3.05 -> 1067.5 | Q74: =D74*F74 -> 2362.8777 | R74: =Q74*$R$67 -> 378.06043 | S74: =Q74-R74 -> 1984.8173
A75: T O T A L S | G75: =SUM(G68:G74) -> 1091157.1 | H75: =SUM(H68:H74) -> 100 | I75: =SUM(I68:I74) -> 0 | J75: =SUM(J68:J74) -> 0 | K75: =SUM(K68:K74) -> 0 | L75: =SUM(L68:L74) -> #REF! | Q75: =SUM(Q68:Q74) -> 301199.01 | R75: =SUM(R68:R74) -> 48191.841 | S75: =SUM(S68:S74) -> 253007.17
O76: =0.85*#REF! -> #REF! | Q76: =Q75*0.0065 -> 1957.7936
Q77: =Q75-Q76 -> 299241.22
F78: % THIS ACCOMPLISHMENT | I78: =L75*100 -> #REF! | K78: %
F79: TOTAL PROJECT COST | I79: =ROUND(G75,2) -> 1091157.1
F80: TOTAL THIS ACCOMPLISHMENT | I80: =J75 -> 0
E81: Less: | F81: MOBILIZATION
F82: TOTAL THIS VOUCHER | I82: =SUM(J75-I81) -> 0
A84: Requested by: | C84: Prepared by: | F84: Checked by: | J84: Approved:
A88: EV INTERIOR CONSTRUCTION | C88: MARISSA A. MACADANGDANG | F88: MA. VICTORIA E. REYES | J88: MANUEL N. MAMBA, M.D.
A89: Contractor | C89: Engineering Assistant | F89: Engineer II | J89: Governor

Sheet STEWA (02-20-26)
A2: Republic of the Philippines
A3: PROVINCE OF CAGAYAN
A4: Capitol Hills, Tuguegarao City
A5: PROVINCIAL ENGINEER'S OFFICE
H6: JUST FILL IN ON BLUE CELL!!! | M6: LEGEND:
A7: STATEMENT OF TIME ELAPSED AND WORK ACCOMPLISHED | M7: single | N7: WITHOUT REVISION
M8: in a relationship | N8: WITH REVISION
B9: =I9 -> 46080 | H9: To be Filled In | I9: 46080 | M9: complicated | N9: ON THE EXPIRY DATE WITHOUT REVISION
M10: married | N10: ON THE EXPIRY DATE WITH REVISION
M11: separated | N11: ON THE COMPLETION DATE WITHOUT REVISION
A12: Project Name | C12: : | D12: =I12 -> REPAIR OF VICENTE TRINIDAD NATIONAL HIGH SCHOOL GYMNASIUM, IGUIG, CAGAYAN | H12: To be Filled In | I12: REPAIR OF VICENTE TRINIDAD NATIONAL HIGH SCHOOL GYMNASIUM, IGUIG, CAGAYAN | J12: Project Name | M12: divorced | N12: ON THE COMPLETION DATE WITH REVISION
A13: Location | C13: : | D13: =I13 -> Iguig, Cagayan | H13: To be Filled In | I13: Iguig, Cagayan | J13: Location | M13: LDR_1 | N13: WITHOUT REVISION
A14: Contract Amount | C14: : | D14: =I14 -> 2396212.4 | H14: To be Filled In | I14: 2396212.4 | J14: Contract Amount | M14: LDR_2 | N14: WITH REVISION
A15: Contractor | C15: : | D15: =I15 -> TS Construction | H15: To be Filled In | I15: TS Construction | J15: Contractor
A17: 1. | B17: Period Covered: | C17: : | D17: =D20+9 -> 45892 | E17: to
D18: =+B9 -> 46080
A19: 2. | B19: Contract Duration | C19: : | D19: =I19 -> 144 | H19: To be Filled In | I19: 144 | J19: Contract Duration
A20: 3. | B20: Date of Receipt of Notice to Proceed | C20: : | D20: =I20 -> 45883 | H20: To be Filled In | I20: 45883 | J20: Date of Receipt of Notice to Proceed
A21: 4. | B21: Expiry Date | C21: : | D21: =+D17+D19 -> 46036
A22: 5. | B22: Approved Time Extension | C22: : | D22: =I22 -> 47 | H22: To be Filled In | I22: 47 | J22: Approved Time Extension
A23: 6. | B23: Approved Time Suspension | C23: : | D23: =I23 -> 0 | H23: To be Filled In | J23: Approved Time Suspension
A24: 7. | B24: Total Time Extension | D24: =IF(I24>0,I24,0) -> 47 | H24: Don't Fill In | I24: =D22 -> 47 | J24: Total Time Extension
A25: 8. | B25: Revised Contract Duration | C25: : | D25: =IF(I24>0,I25,0) -> 191 | H25: Don't Fill In | I25: =IF(D22>0,D22+I19,0) -> 191 | J25: Revised Contract Duration
A26: 9. | B26: Revised Expiry Date | C26: : | D26: =D21+D24 -> 46083
A27: 10. | B27: Total Calendar days Elapsed to Date | C27: : | D27: =+D18-D17-D23 -> 188
A28: 11. | B28: Percentage of work accomplished - Actual | C28: : | D28: =#REF! -> #REF! | I28: =#REF! -> #REF! | J28: (FROM SWA)
A29: 12. | B29: Percentage of work accomplished -Planned | C29: : | D29: =I30 -> 1 | H29: Don't Fill In | I29: =(((SIN((((180*((D27))/D19)-90)*(3.14159265358979/180)))+1)*50)/100) -> 0.78678822 | J29: W/ FORMULA - Planned (WITHOUT time extension)
A30: 13. | B30: Slippage | C30: : | D30: =D28-D29 -> #REF! | H30: Don't Fill In | I30: =I33 -> 1 | J30: W/ FORMULA - Planned (WITH time extension)
A31: 14. | B31: Remarks | C31: :
H32: Don't Fill In | I32: =D27/D19 -> 1.3055556 | J32: LINEAR - Planned (WITHOUT time extension)
H33: Don't Fill In | I33: 1 | J33: LINEAR - Planned (WITH time extension)
B35: Submitted by: | D35: Noted by: | H35: F | I35: WRITE "F" - OPT TO USE FORMULA
I36: WRITE "L" - OPT TO USE LINEAR
B38: DIXIE R. CABRERA | D38: KATHLEEN MEI P. BAGASIN
B39: Engineer II | D39: Engineer IV (Chief-Construction Division)

Sheet STEWA (July 26, 2024)
A2: Republic of the Philippines
A3: PROVINCE OF CAGAYAN
A4: Capitol Hills, Tuguegarao City
A5: PROVINCIAL ENGINEER'S OFFICE
H6: JUST FILL IN ON BLUE CELL!!! | M6: LEGEND:
A7: STATEMENT OF TIME ELAPSED AND WORK ACCOMPLISHED | M7: single | N7: WITHOUT REVISION
M8: in a relationship | N8: WITH REVISION
B9: =I9 -> July 26, 2024 | H9: To be Filled In | I9: July 26, 2024 | M9: complicated | N9: ON THE EXPIRY DATE WITHOUT REVISION
M10: married | N10: ON THE EXPIRY DATE WITH REVISION
M11: separated | N11: ON THE COMPLETION DATE WITHOUT REVISION
A12: Project Name | C12: : | D12: =I12 -> Construction of Multi-Purpose Building Lallo National High School | H12: To be Filled In | I12: Construction of Multi-Purpose Building Lallo National High School | J12: Project Name | M12: divorced | N12: ON THE COMPLETION DATE WITH REVISION
A13: Location | C13: : | D13: =I13 -> Lallo, Cagayan | H13: To be Filled In | I13: Lallo, Cagayan | J13: Location | M13: LDR_1 | N13: WITHOUT REVISION
A14: Contract Amount | C14: : | D14: =I14 -> 3796932.5 | H14: To be Filled In | I14: 3796932.5 | J14: Contract Amount | M14: LDR_2 | N14: WITH REVISION
A15: Contractor | C15: : | D15: =I15 -> Rucs Konsult and Construction Services | H15: To be Filled In | I15: Rucs Konsult and Construction Services | J15: Contractor
A17: 1. | B17: Period Covered: | C17: : | D17: =D20+9 -> 45045 | E17: to
D18: =+B9 -> July 26, 2024
A19: 2. | B19: Contract Duration | C19: : | D19: =I19 -> 180 | H19: To be Filled In | I19: 180 | J19: Contract Duration
A20: 3. | B20: Date of Receipt of Notice to Proceed | C20: : | D20: =I20 -> 45036 | H20: To be Filled In | I20: 45036 | J20: Date of Receipt of Notice to Proceed
A21: 4. | B21: Expiry Date | C21: : | D21: =+D17+D19 -> 45225
A22: 5. | B22: Approved Time Extension | C22: : | D22: =I22 -> 0 | H22: To be Filled In | J22: Approved Time Extension
A23: 6. | B23: Approved Time Suspension | C23: : | D23: 446 | H23: To be Filled In | I23: 450 | J23: Approved Time Suspension
A24: 7. | B24: Total Time Extension | D24: =IF(I24>0,I24,0) -> 0 | H24: Don't Fill In | I24: =D22 -> 0 | J24: Total Time Extension
A25: 8. | B25: Revised Contract Duration | C25: : | D25: =IF(I24>0,I25,0) -> 0 | H25: Don't Fill In | I25: =IF(D22>0,D22+I19,0)-1 -> -1 | J25: Revised Contract Duration
A26: 9. | B26: Revised Expiry Date | C26: : | D26: =D21+D23 -> 45671
A27: 10. | B27: Total Calendar days Elapsed to Date | C27: : | D27: =+D18-D17+1 -> 455
A28: 11. | B28: Percentage of work accomplished - Actual | C28: : | D28: =#REF! -> #REF! | I28: =#REF! -> #REF! | J28: (FROM SWA)
A29: 12. | B29: Percentage of work accomplished -Planned | C29: : | D29: =I29 -> 0.54357787 | H29: Don't Fill In | I29: =(((SIN((((180*((D27))/D19)-90)*(3.14159265358979/180)))+1)*50)/100) -> 0.54357787 | J29: W/ FORMULA - Planned (WITHOUT time extension)
A30: 13. | B30: Slippage | C30: : | D30: =D28-D29 -> #REF! | H30: Don't Fill In | I30: =IF(I25>0,(((SIN((((180*((D27))/D25)-90)*(3.14159265358979/180)))+1)*50)/100),"") | J30: W/ FORMULA - Planned (WITH time extension)
A31: 14. | B31: Remarks | C31: :
H32: Don't Fill In | I32: =D27/D19 -> 2.5277778 | J32: LINEAR - Planned (WITHOUT time extension)
H33: Don't Fill In | I33: 1 | J33: LINEAR - Planned (WITH time extension)
B35: Submitted by: | D35: Noted by: | H35: F | I35: WRITE "F" - OPT TO USE FORMULA
I36: WRITE "L" - OPT TO USE LINEAR
B38: MARK KEVIN B. MARTIN | D38: KATHLEEN MEI P. BAGASIN
B39: Engineer II | D39: Engineer IV (Chief-Construction Division)

Sheet STEWA (August 16, 2024)
A2: Republic of the Philippines
A3: PROVINCE OF CAGAYAN
A4: Capitol Hills, Tuguegarao City
A5: PROVINCIAL ENGINEER'S OFFICE
H6: JUST FILL IN ON BLUE CELL!!! | M6: LEGEND:
A7: STATEMENT OF TIME ELAPSED AND WORK ACCOMPLISHED | M7: single | N7: WITHOUT REVISION
M8: in a relationship | N8: WITH REVISION
B9: =I9 -> 45541 | H9: To be Filled In | I9: 45541 | M9: complicated | N9: ON THE EXPIRY DATE WITHOUT REVISION
M10: married | N10: ON THE EXPIRY DATE WITH REVISION
M11: separated | N11: ON THE COMPLETION DATE WITHOUT REVISION
A12: Project Name | C12: : | D12: =I12 -> Construction of Multi-Purpose Building Lallo National High School | H12: To be Filled In | I12: Construction of Multi-Purpose Building Lallo National High School | J12: Project Name | M12: divorced | N12: ON THE COMPLETION DATE WITH REVISION
A13: Location | C13: : | D13: =I13 -> Lallo, Cagayan | H13: To be Filled In | I13: Lallo, Cagayan | J13: Location | M13: LDR_1 | N13: WITHOUT REVISION
A14: Contract Amount | C14: : | D14: =I14 -> 3796932.5 | H14: To be Filled In | I14: 3796932.5 | J14: Contract Amount | M14: LDR_2 | N14: WITH REVISION
A15: Contractor | C15: : | D15: =I15 -> Rucs Konsult and Construction Services | H15: To be Filled In | I15: Rucs Konsult and Construction Services | J15: Contractor
A17: 1. | B17: Period Covered: | C17: : | D17: =D20+9 -> 45045 | E17: to
D18: =+B9 -> 45541
A19: 2. | B19: Contract Duration | C19: : | D19: =I19 -> 180 | H19: To be Filled In | I19: 180 | J19: Contract Duration
A20: 3. | B20: Date of Receipt of Notice to Proceed | C20: : | D20: =I20 -> 45036 | H20: To be Filled In | I20: 45036 | J20: Date of Receipt of Notice to Proceed
A21: 4. | B21: Expiry Date | C21: : | D21: =+D17+D19 -> 45225
A22: 5. | B22: Approved Time Extension | C22: : | D22: =I22 -> 0 | H22: To be Filled In | J22: Approved Time Extension
A23: 6. | B23: Approved Time Suspension | C23: : | D23: 446 | H23: To be Filled In | I23: 450 | J23: Approved Time Suspension
A24: 7. | B24: Total Time Extension | D24: =IF(I24>0,I24,0) -> 0 | H24: Don't Fill In | I24: =D22 -> 0 | J24: Total Time Extension
A25: 8. | B25: Revised Contract Duration | C25: : | D25: =IF(I24>0,I25,0) -> 0 | H25: Don't Fill In | I25: =IF(D22>0,D22+I19,0)-1 -> -1 | J25: Revised Contract Duration
A26: 9. | B26: Revised Expiry Date | C26: : | D26: =D21+D23 -> 45671
A27: 10. | B27: Total Calendar days Elapsed to Date | C27: : | D27: =+D18-D17+1-D23 -> 51
A28: 11. | B28: Percentage of work accomplished - Actual | C28: : | D28: =#REF! -> #REF! | I28: =#REF! -> #REF! | J28: (FROM SWA)
A29: 12. | B29: Percentage of work accomplished -Planned | C29: : | D29: =I29 -> 0.1853398 | H29: Don't Fill In | I29: =(((SIN((((180*((D27))/D19)-90)*(3.14159265358979/180)))+1)*50)/100) -> 0.1853398 | J29: W/ FORMULA - Planned (WITHOUT time extension)
A30: 13. | B30: Slippage | C30: : | D30: =D28-D29 -> #REF! | H30: Don't Fill In | I30: =IF(I25>0,(((SIN((((180*((D27))/D25)-90)*(3.14159265358979/180)))+1)*50)/100),"") | J30: W/ FORMULA - Planned (WITH time extension)
A31: 14. | B31: Remarks | C31: :
H32: Don't Fill In | I32: =D27/D19 -> 0.28333333 | J32: LINEAR - Planned (WITHOUT time extension)
H33: Don't Fill In | I33: 1 | J33: LINEAR - Planned (WITH time extension)
B35: Submitted by: | D35: Noted by: | H35: F | I35: WRITE "F" - OPT TO USE FORMULA
I36: WRITE "L" - OPT TO USE LINEAR
B38: MARK KEVIN B. MARTIN | D38: KATHLEEN MEI P. BAGASIN
B39: Engineer II | D39: Engineer IV (Chief-Construction Division)

Sheet SWA (August 23, 2024)
B1: STATEMENT OF WORK ACCOMPLISHMENT
F2: As of | G2: ='STEWA (August 16, 2024)'!I9 -> 45541
A4: Project Title: | B4: ='STEWA (August 16, 2024)'!I12 -> Construction of Multi-Purpose Building Lallo National High School
A5: Location: | B5: ='STEWA (August 16, 2024)'!I13 -> Lallo, Cagayan
A7: ITEM | B7: DESCRIPTION OF WORK | D7: PROGRAMMED | F7: UNIT | G7: CONTRACT | H7: WEIGHT | I7: ACCOMPLISHMENT | L7: WEIGHT | M7: REMARKS/ | P7: 802 | Q7: Excavation
A8: NO. | D8: QUANTITY | F8: PRICE | G8: AMOUNT | H8: % | I8: PREVIOUS | J8: THIS PERIOD | K8: TO DATE | L8: % | M8: STATUS | N8: =#REF!/6.1 -> #REF! | P8: Length | Q8: Width | R8: Height | S8: Qty | T8: Volume | U8: Unit
D9: ORIGINAL | N9: 650 | P9: 1.5 | Q9: 1.5 | R9: 1.5 | S9: 4 | T9: =P9*Q9*R9*S9 -> 13.5 | U9: =E15 -> cu.m
A10: I | B10: OTHER GENERAL REQUIREMENTS
A11: B.5 | B11: Project Billboard | D11: 2 | E11: each | F11: 14849.21 | G11: =ROUND(F11*D11,2) -> 29698.42 | H11: =ROUND((G11/$G$31),5) -> 0.00744 | I11: =#REF! -> #REF! | J11: =K11-I11 -> #REF! | K11: 0 | L11: =ROUND(K11/$G$31,5) -> 0 | M11: =IF(L11=H11,"COMPLETED",IF(L11=0,"Not Yet Started","On going")) -> Not Yet Started | N11: =(J11/G11)*D11 -> #REF! | P11: 804(b) | Q11: Gravel Bedding
A12: B.7 | B12: Construction Safety and Health Program | D12: 1 | E12: l.s | F12: 52524.01 | G12: =F12 -> 52524.01 | H12: =ROUND((G12/$G$31),5) -> 0.01316 | I12: =#REF! -> #REF! | J12: =K12-I12 -> #REF! | K12: =(10/210)*G12 -> 2501.1433 | L12: =ROUND(K12/$G$31,5) -> 0.00063 | M12: =IF(L12=H12,"COMPLETED",IF(L12=0,"Not Yet Started","On going")) -> On going | N12: =(J12/G12)*D12 -> #REF! | P12: Length | Q12: Width | R12: Thickness | S12: Qty | T12: Volume | U12: Unit
A13: B.9 | B13: Mobilization/ Demobilization | D13: 1 | E13: l.s | F13: 31020.38 | G13: =F13 -> 31020.38 | H13: =ROUND((G13/$G$31),5) -> 0.00777 | I13: =#REF! -> #REF! | J13: =K13-I13 -> #REF! | K13: =0.5*G13 -> 15510.19 | L13: =ROUND(K13/$G$31,5) -> 0.00389 | M13: =IF(L13=H13,"COMPLETED",IF(L13=0,"Not Yet Started","On going")) -> On going | N13: =(J13/G13)*D13 -> #REF! | P13: 1.5 | Q13: 1.5 | R13: 0.1 | T13: =P13*Q13*R13*S13 -> 0 | U13: =E19 -> cu.m
A14: II | B14: WORK ITEMS
A15: 802 | B15: Excavation | D15: 92.65 | E15: cu.m | F15: 221.94 | G15: =ROUND(F15*D15,2) -> 20562.74 | H15: =ROUND((G15/$G$31),5) -> 0.00515 | I15: =#REF! -> #REF! | J15: =T9*F15 -> 2996.19 | K15: =G15*0.4 -> 8225.096 | L15: =ROUND(K15/$G$31,5) -> 0.00206 | M15: =IF(L15=H15,"COMPLETED",IF(L15=0,"Not Yet Started","On going")) -> On going | N15: =(J15/G15)*D15 -> 13.500001 | P15: 900 (a) | Q15: Reinforced Concrete Column Footing
A16: 804(a) | B16: Backfilling | D16: 32.4 | E16: cu.m | F16: 55.17 | G16: =ROUND(F16*D16,2) -> 1787.51 | H16: =ROUND((G16/$G$31),5) -> 0.00045 | I16: =#REF! -> #REF! | J16: =K16-I16 -> #REF! | K16: 0 | L16: =ROUND(K16/$G$31,5) -> 0 | M16: =IF(L16=H16,"COMPLETED",IF(L16=0,"Not Yet Started","On going")) -> Not Yet Started | N16: =(J16/G16)*D16 -> #REF! | P16: Length | Q16: Width | R16: Thickness | S16: Qty | T16: Volume | U16: Unit
A17: 804(b) | B17: Gravel Bedding | D17: 54.66 | E17: cu.m | F17: 813.59 | G17: =ROUND(F17*D17,2) -> 44470.83 | H17: =ROUND((G17/$G$31),5) -> 0.01114 | I17: =#REF! -> #REF! | J17: =T13*F17 -> 0 | L17: =ROUND(K17/$G$31,5) -> 0 | M17: =IF(L17=H17,"COMPLETED",IF(L17=0,"Not Yet Started","On going")) -> Not Yet Started | N17: =(J17/G17)*D17 -> 0 | P17: 1.5 | Q17: 1.5 | R17: 0.35 | T17: =P17*Q17*R17*S17 -> 0 | U17: =E23 -> sq.m.
A18: 900 (a) | B18: Reinforced Concrete Column Footing | D18: 9.45 | E18: cu.m | F18: 16311.68 | G18: =ROUND(F18*D18,2) -> 154145.38 | H18: =ROUND((G18/$G$31),5) -> 0.03862 | I18: =#REF! -> #REF! | J18: =T17*F18 -> 0 | L18: =ROUND(K18/$G$31,5) -> 0 | M18: =IF(L18=H18,"COMPLETED",IF(L18=0,"Not Yet Started","On going")) -> Not Yet Started | N18: =(J18/G18)*D18 -> 0
A19: 901 (b) | B19: Reinforced Concrete Wall Footing | D19: 3.12 | E19: cu.m | F19: 17371.06 | G19: =ROUND(F19*D19,2) -> 54197.71 | H19: =ROUND((G19/$G$31),5) -> 0.01358 | I19: =#REF! -> #REF! | J19: =K19-I19 -> #REF! | K19: 0 | L19: =ROUND(K19/$G$31,5) -> 0 | M19: =IF(L19=H19,"COMPLETED",IF(L19=0,"Not Yet Started","On going")) -> Not Yet Started | N19: =(J19/G19)*D19 -> #REF!
A20: 902 (c) | B20: Reinforced Concrete Column and Corbel | D20: 16.32 | E20: cu.m | F20: 22958.55 | G20: =ROUND(F20*D20,2) -> 374683.54 | H20: =ROUND((G20/$G$31),5) -> 0.09389 | I20: =#REF! -> #REF! | J20: =K20-I20 -> #REF! | K20: 0 | L20: =ROUND(K20/$G$31,5) -> 0 | M20: =IF(L20=H20,"COMPLETED",IF(L20=0,"Not Yet Started","On going")) -> Not Yet Started | N20: =(J20/G20)*D20 -> #REF!
A21: 903 (d) | B21: Reinforced Concrete Beams | D21: 5.6 | E21: cu.m | F21: 26671.53 | G21: =ROUND(F21*D21,2) -> 149360.57 | H21: =ROUND((G21/$G$31),5) -> 0.03743 | I21: =#REF! -> #REF! | J21: =K21-I21 -> #REF! | K21: 0 | L21: =ROUND(K21/$G$31,5) -> 0 | M21: =IF(L21=H21,"COMPLETED",IF(L21=0,"Not Yet Started","On going")) -> Not Yet Started | N21: =(J21/G21)*D21 -> #REF!
A22: 904 (e) | B22: Reinforced Concrete Slab | D22: 50.4 | E22: cu.m | F22: 9441 | G22: =ROUND(F22*D22,2) -> 475826.4 | H22: =ROUND((G22/$G$31),5) -> 0.11923 | I22: =#REF! -> #REF! | J22: =K22-I22 -> #REF! | K22: 0 | L22: =ROUND(K22/$G$31,5) -> 0 | M22: =IF(L22=H22,"COMPLETED",IF(L22=0,"Not Yet Started","On going")) -> Not Yet Started | N22: =(J22/G22)*D22 -> #REF!
A23: 903 | B23: Formworks and Falseworks | D23: 108 | E23: sq.m. | F23: 3583.04 | G23: =ROUND(F23*D23,2) -> 386968.32 | H23: =ROUND((G23/$G$31),5) -> 0.09696 | I23: =#REF! -> #REF! | J23: =K23-I23 -> #REF! | L23: =ROUND(K23/$G$31,5) -> 0 | M23: =IF(L23=H23,"COMPLETED",IF(L23=0,"Not Yet Started","On going")) -> Not Yet Started | N23: =(J23/G23)*D23 -> #REF!
A24: 1046 | B24: Masonry Works | D24: 36.8 | E24: sq.m. | F24: 968.36 | G24: =ROUND(F24*D24,2) -> 35635.65 | H24: =ROUND((G24/$G$31),5) -> 0.00893 | I24: =#REF! -> #REF! | J24: =K24-I24 -> #REF! | L24: =ROUND(K24/$G$31,5) -> 0 | M24: =IF(L24=H24,"COMPLETED",IF(L24=0,"Not Yet Started","On going")) -> Not Yet Started | N24: =(J24/G24)*D24 -> #REF!
A25: 1027 | B25: Cement Plaster Finish | D25: 212.76 | E25: sq.m. | F25: 55.61 | G25: =ROUND(F25*D25,2) -> 11831.58 | H25: =ROUND((G25/$G$31),5) -> 0.00296 | I25: =#REF! -> #REF! | J25: =K25-I25 -> #REF! | L25: =ROUND(K25/$G$31,5) -> 0 | M25: =IF(L25=H25,"COMPLETED",IF(L25=0,"Not Yet Started","On going")) -> Not Yet Started | N25: =(J25/G25)*D25 -> #REF!
A26: 1032 | B26: Painting Works | D26: 194.36 | E26: sq.m. | F26: 358.8 | G26: =ROUND(F26*D26,2) -> 69736.37 | H26: =ROUND((G26/$G$31),5) -> 0.01747 | I26: =#REF! -> #REF! | J26: =K26-I26 -> #REF! | K26: 0 | L26: =ROUND(K26/$G$31,5) -> 0 | M26: =IF(L26=H26,"COMPLETED",IF(L26=0,"Not Yet Started","On going")) -> Not Yet Started | N26: =(J26/G26)*D26 -> #REF!
A27: 1047 | B27: Metal Structure | D27: 16113.92 | E27: kgs. | F27: 90.41 | G27: =ROUND(F27*D27,2) -> 1456859.5 | H27: =ROUND((G27/$G$31),5) -> 0.36505 | I27: =#REF! -> #REF! | J27: =K27-I27 -> #REF! | L27: =ROUND(K27/$G$31,5) -> 0 | M27: =IF(L27=H27,"COMPLETED",IF(L27=0,"Not Yet Started","On going")) -> Not Yet Started | N27: =(J27/G27)*D27 -> #REF!
A28: 1013(a) | B28: Corrugated Asphalt Roof | D28: 684 | E28: sq.m. | F28: 793.5 | G28: =ROUND(F28*D28,2) -> 542754 | H28: =ROUND((G28/$G$31),5) -> 0.136 | I28: =#REF! -> #REF! | J28: =K28-I28 -> #REF! | K28: 0 | L28: =ROUND(K28/$G$31,5) -> 0 | M28: =IF(L28=H28,"COMPLETED",IF(L28=0,"Not Yet Started","On going")) -> Not Yet Started | N28: =(J28/G28)*D28 -> #REF!
A29: 1103 | B29: Electrical Works | D29: 12 | E29: units | F29: 8231.21 | G29: =ROUND(F29*D29,2) -> 98774.52 | H29: =ROUND((G29/$G$31),5) -> 0.02475 | I29: =#REF! -> #REF! | J29: =K29-I29 -> #REF! | L29: =ROUND(K29/$G$31,5) -> 0 | M29: =IF(L29=H29,"COMPLETED",IF(L29=0,"Not Yet Started","On going")) -> Not Yet Started | N29: =(J29/G29)*D29 -> #REF!
A31: T O T A L S | G31: =SUM(G10:G30) -> 3990837.4 | H31: =SUM(H10:H29) -> 0.99998 | J31: =SUM(J10:J30) -> #REF! | K31: =SUM(K10:K30) -> 26236.429 | L31: =SUM(L10:L29) -> 0.00658
F34: % THIS ACCOMPLISHMENT | I34: =L31 -> 0.00658
F35: TOTAL PROJECT COST | I35: =G31 -> 3990837.4
F36: TOTAL THIS ACCOMPLISHMENT | I36: =J31 -> #REF!
E37: Less: | F37: MOBILIZATION
F38: TOTAL THIS VOUCHER | I38: =SUM(J31-I37) -> #REF!
A40: Prepared by: | C40: Checked by: | G40: Recommending Approval: | K40: Approved:
A44: MARK KEVIN B. MARTIN | C44: KATHLEEN MEI P. BAGASIN | G44: KINGSTON JAMES S. DELA CRUZ | K44: MANUEL N. MAMBA, M.D.
A45: Engineer II | C45: Chief of Construction Division | G45: Provincial Engineer | K45: Governor
B47: =B1 -> STATEMENT OF WORK ACCOMPLISHMENT
B48: As of _____________________, 2020
A50: A. | B50: ='[2]SWA(abd)'!B12 -> CONCRETING OF FARM TO MARKET ROAD ZIMINILA
B51: ='[2]SWA(abd)'!B13 -> CAMALANIUGAN, CAGAYAN
A53: ITEM | B53: DESCRIPTION OF WORK | D53: PROGRAMMED | F53: UNIT | G53: CONTRACT | H53: WEIGHT | I53: ACCOMPLISHMENT | L53: WEIGHT | M53: REMARKS/
A54: NO. | D54: QUANTITY | F54: PRICE | G54: AMOUNT | H54: % | I54: PREVIOUS | J54: THIS PERIOD | K54: TO DATE | L54: % | M54: STATUS
D55: ORIGINAL | R55: 0.16
A56: ='[2]SWA(abd)'!A17 -> 105(1) | B56: ='[2]SWA(abd)'!B17:C17 -> Sub Grade Preparation | D56: ='[2]SWA(abd)'!D17 -> 1075.8 | E56: ='[2]SWA(abd)'!E17 -> sq.m. | F56: ='[2]SWA(abd)'!F17 -> 102.17 | G56: ='[2]SWA(abd)'!G17 -> 109364.91 | H56: =(G56/$G$63)*100 -> 10.022838 | K56: =I56+J56 -> 0 | L56: =ROUND(K56/#REF!,4) -> #REF! | M56: on-going | Q56: =D56*F56 -> 109914.49 | R56: =Q56*$R$55 -> 17586.318 | S56: =Q56-R56 -> 92328.168
A57: ='[2]SWA(abd)'!A18 -> 200(1) | B57: ='[2]SWA(abd)'!B18:C18 -> Aggregate Sub Base Coarse | D57: ='[2]SWA(abd)'!D18 -> 173.25 | E57: ='[2]SWA(abd)'!E18 -> sq.m. | F57: 804.58 | G57: ='[2]SWA(abd)'!G18 -> 223636.89 | H57: =(G57/$G$63)*100 -> 20.495388 | K57: =I57+J57 -> 0 | L57: =ROUND(K57/$G$63,4) -> 0 | M57: on-going | Q57: =D57*F57 -> 139393.49 | R57: =Q57*$R$55 -> 22302.958 | S57: =Q57-R57 -> 117090.53
A58: ='[2]SWA(abd)'!A19 -> 311(1)C | B58: ='[2]SWA(abd)'!B19:C19 -> PCCP | D58: ='[2]SWA(abd)'!D19 -> 660 | E58: ='[2]SWA(abd)'!E19 -> sq.m. | F58: 72.96 | G58: ='[2]SWA(abd)'!G19 -> 672973.03 | H58: =(G58/$G$63)*100 -> 61.675171 | K58: =I58+J58 -> 0 | L58: =ROUND(K58/$G$63,4) -> 0 | M58: on-going | O58: =0.2*#REF! -> #REF! | P58: =0.95*#REF! -> #REF! | Q58: =D58*F58 -> 48153.6 | R58: =Q58*$R$55 -> 7704.576 | S58: =Q58-R58 -> 40449.024
A59: ='[2]SWA(abd)'!A20 -> B.9 | B59: ='[2]SWA(abd)'!B20:C20 -> Mobilization/ Demobilization | D59: ='[2]SWA(abd)'!D20 -> 1 | E59: ='[2]SWA(abd)'!E20 -> l/s | F59: 128.93 | G59: ='[2]SWA(abd)'!G20 -> 25951.88 | H59: =(G59/$G$63)*100 -> 2.3783815 | K59: =I59+J59 -> 0 | L59: =ROUND(K59/$G$63,4) -> 0 | M59: on-going | O59: 604.87 | P59: =0.95*#REF! -> #REF! | Q59: =D59*F59 -> 128.93 | R59: =Q59*$R$55 -> 20.6288 | S59: =Q59-R59 -> 108.3012
A60: ='[2]SWA(abd)'!A21 -> B.5 | B60: ='[2]SWA(abd)'!B21:C21 -> Billboards and Signages | D60: ='[2]SWA(abd)'!D21 -> 2 | E60: ='[2]SWA(abd)'!E21 -> each | F60: 18.37 | G60: ='[2]SWA(abd)'!G21 -> 10196.76 | H60: =(G60/$G$63)*100 -> 0.93449052 | K60: =I60+J60 -> 0 | L60: =ROUND(K60/$G$63,4) -> 0 | M60: on-going | O60: =0.2*#REF! -> #REF! | P60: =0.95*#REF! -> #REF! | Q60: =D60*F60 -> 36.74 | R60: =Q60*$R$55 -> 5.8784 | S60: =Q60-R60 -> 30.8616
A61: ='[2]SWA(abd)'!A22 -> B.7 | B61: ='[2]SWA(abd)'!B22:C22 -> Occupational Health and Safety | D61: ='[2]SWA(abd)'!D22 -> 1 | E61: ='[2]SWA(abd)'!E22 -> l/s | F61: 1208.89 | G61: ='[2]SWA(abd)'!G22 -> 28041.09 | H61: =(G61/$G$63)*100 -> 2.5698489 | K61: =I61+J61 -> 0 | L61: =ROUND(K61/$G$63,4) -> 0 | M61: on-going | O61: =0.2*#REF! -> #REF! | P61: =0.9*#REF! -> #REF! | Q61: =D61*F61 -> 1208.89 | R61: =Q61*$R$55 -> 193.4224 | S61: =Q61-R61 -> 1015.4676
A62: ='[2]SWA(abd)'!A23 -> A.1.1(8a) | B62: ='[2]SWA(abd)'!B23:C23 -> Provisions of Field Office for the Engineer | D62: ='[2]SWA(abd)'!D23 -> 1.83 | E62: ='[2]SWA(abd)'!E23 -> mos | F62: 1291.19 | G62: ='[2]SWA(abd)'!G23 -> 20992.58 | H62: =(G62/$G$63)*100 -> 1.9238824 | K62: =I62+J62 -> 0 | L62: =ROUND(K62/$G$63,4) -> 0 | M62: on-going | O62: =350*3.05 -> 1067.5 | Q62: =D62*F62 -> 2362.8777 | R62: =Q62*$R$55 -> 378.06043 | S62: =Q62-R62 -> 1984.8173
A63: T O T A L S | G63: =SUM(G56:G62) -> 1091157.1 | H63: =SUM(H56:H62) -> 100 | I63: =SUM(I56:I62) -> 0 | J63: =SUM(J56:J62) -> 0 | K63: =SUM(K56:K62) -> 0 | L63: =SUM(L56:L62) -> #REF! | Q63: =SUM(Q56:Q62) -> 301199.01 | R63: =SUM(R56:R62) -> 48191.841 | S63: =SUM(S56:S62) -> 253007.17
O64: =0.85*#REF! -> #REF! | Q64: =Q63*0.0065 -> 1957.7936
Q65: =Q63-Q64 -> 299241.22
F66: % THIS ACCOMPLISHMENT | I66: =L63*100 -> #REF! | K66: %
F67: TOTAL PROJECT COST | I67: =ROUND(G63,2) -> 1091157.1
F68: TOTAL THIS ACCOMPLISHMENT | I68: =J63 -> 0
E69: Less: | F69: MOBILIZATION
F70: TOTAL THIS VOUCHER | I70: =SUM(J63-I69) -> 0
A72: Requested by: | C72: Prepared by: | F72: Checked by: | J72: Approved:
A76: EV INTERIOR CONSTRUCTION | C76: MARISSA A. MACADANGDANG | F76: MA. VICTORIA E. REYES | J76: MANUEL N. MAMBA, M.D.
A77: Contractor | C77: Engineering Assistant | F77: Engineer II | J77: Governor

Sheet STEWA (August 23, 2024)
A2: Republic of the Philippines
A3: PROVINCE OF CAGAYAN
A4: Capitol Hills, Tuguegarao City
A5: PROVINCIAL ENGINEER'S OFFICE
H6: JUST FILL IN ON BLUE CELL!!! | M6: LEGEND:
A7: STATEMENT OF TIME ELAPSED AND WORK ACCOMPLISHED | M7: single | N7: WITHOUT REVISION
M8: in a relationship | N8: WITH REVISION
B9: =I9 -> 45527 | H9: To be Filled In | I9: 45527 | M9: complicated | N9: ON THE EXPIRY DATE WITHOUT REVISION
M10: married | N10: ON THE EXPIRY DATE WITH REVISION
M11: separated | N11: ON THE COMPLETION DATE WITHOUT REVISION
A12: Project Name | C12: : | D12: =I12 -> Construction of Multi-Purpose Building Lallo National High School | H12: To be Filled In | I12: Construction of Multi-Purpose Building Lallo National High School | J12: Project Name | M12: divorced | N12: ON THE COMPLETION DATE WITH REVISION
A13: Location | C13: : | D13: =I13 -> Lallo, Cagayan | H13: To be Filled In | I13: Lallo, Cagayan | J13: Location | M13: LDR_1 | N13: WITHOUT REVISION
A14: Contract Amount | C14: : | D14: =I14 -> 3990443.9 | H14: To be Filled In | I14: 3990443.9 | J14: Contract Amount | M14: LDR_2 | N14: WITH REVISION
A15: Contractor | C15: : | D15: =I15 -> RUCS Construction | H15: To be Filled In | I15: RUCS Construction | J15: Contractor
A17: 1. | B17: Period Covered: | C17: : | D17: =D20+9 -> 45511 | E17: to
D18: =+B9 -> 45527
A19: 2. | B19: Contract Duration | C19: : | D19: =I19 -> 210 | H19: To be Filled In | I19: 210 | J19: Contract Duration
A20: 3. | B20: Date of Receipt of Notice to Proceed | C20: : | D20: =I20 -> 45502 | H20: To be Filled In | I20: 45502 | J20: Date of Receipt of Notice to Proceed
A21: 4. | B21: Expiry Date | C21: : | D21: =+D17+D19 -> 45721
A22: 5. | B22: Approved Time Extension | C22: : | D22: =D23+I22 -> 0 | H22: To be Filled In | J22: Approved Time Extension
A23: 6. | B23: Approved Time Suspension | C23: : | D23: =I23 -> 0 | H23: To be Filled In | J23: Approved Time Suspension
A24: 7. | B24: Total Time Extension | D24: =IF(I24>0,I24,0) -> 0 | H24: Don't Fill In | I24: =D22 -> 0 | J24: Total Time Extension
A25: 8. | B25: Revised Contract Duration | C25: : | D25: =IF(I24>0,I25,0) -> 0 | H25: Don't Fill In | I25: =IF(D22>0,D22+I19,0)-1 -> -1 | J25: Revised Contract Duration
A26: 9. | B26: Revised Expiry Date | C26: : | D26: =IF(I25>0,I26,0) -> 0
A27: 10. | B27: Total Calendar days Elapsed to Date | C27: : | D27: =+D18-D17+1 -> 17
A28: 11. | B28: Percentage of work accomplished - Actual | C28: : | D28: =#REF! -> #REF! | I28: =#REF! -> #REF! | J28: (FROM SWA)
A29: 12. | B29: Percentage of work accomplished -Planned | C29: : | D29: =I29 -> 0.016082626 | H29: Don't Fill In | I29: =(((SIN((((180*((D27))/D19)-90)*(3.14159265358979/180)))+1)*50)/100) -> 0.016082626 | J29: W/ FORMULA - Planned (WITHOUT time extension)
A30: 13. | B30: Slippage | C30: : | D30: =D28-D29 -> #REF! | H30: Don't Fill In | I30: =IF(I25>0,(((SIN((((180*((D27))/D25)-90)*(3.14159265358979/180)))+1)*50)/100),"") | J30: W/ FORMULA - Planned (WITH time extension)
A31: 14. | B31: Remarks | C31: :
H32: Don't Fill In | I32: =D27/D19 -> 0.080952381 | J32: LINEAR - Planned (WITHOUT time extension)
H33: Don't Fill In | I33: 1 | J33: LINEAR - Planned (WITH time extension)
B35: Submitted by: | D35: Noted by: | H35: F | I35: WRITE "F" - OPT TO USE FORMULA
I36: WRITE "L" - OPT TO USE LINEAR
B38: MARK KEVIN B. MARTIN | D38: KATHLEEN MEI P. BAGASIN
B39: Engineer II | D39: Engineer IV (Chief-Construction Division)

Sheet SWA (August 30, 2024)
B1: STATEMENT OF WORK ACCOMPLISHMENT
F2: As of | G2: ='STEWA (August 30, 2024)'!I9 -> 45534
A4: Project Title: | B4: ='STEWA (August 16, 2024)'!I12 -> Construction of Multi-Purpose Building Lallo National High School
A5: Location: | B5: ='STEWA (August 16, 2024)'!I13 -> Lallo, Cagayan
A7: ITEM | B7: DESCRIPTION OF WORK | D7: PROGRAMMED | F7: UNIT | G7: CONTRACT | H7: WEIGHT | I7: ACCOMPLISHMENT | L7: WEIGHT | M7: REMARKS/ | P7: 802 | Q7: Excavation
A8: NO. | D8: QUANTITY | F8: PRICE | G8: AMOUNT | H8: % | I8: PREVIOUS | J8: THIS PERIOD | K8: TO DATE | L8: % | M8: STATUS | N8: =#REF!/6.1 -> #REF! | P8: Length | Q8: Width | R8: Height | S8: Qty | T8: Volume | U8: Unit
D9: ORIGINAL | N9: 650 | P9: 1.5 | Q9: 1.5 | R9: 1.5 | S9: 4 | T9: =P9*Q9*R9*S9 -> 13.5 | U9: =E15 -> cu.m
A10: I | B10: OTHER GENERAL REQUIREMENTS
A11: B.5 | B11: Project Billboard | D11: 2 | E11: each | F11: 14849.21 | G11: =ROUND(F11*D11,2) -> 29698.42 | H11: =ROUND((G11/$G$31),5) -> 0.00744 | I11: =#REF! -> #REF! | J11: =K11-I11 -> #REF! | K11: 0 | L11: =ROUND(K11/$G$31,5) -> 0 | M11: =IF(L11=H11,"COMPLETED",IF(L11=0,"Not Yet Started","On going")) -> Not Yet Started | N11: =(J11/G11)*D11 -> #REF! | P11: 804(b) | Q11: Gravel Bedding
A12: B.7 | B12: Construction Safety and Health Program | D12: 1 | E12: l.s | F12: 52524.01 | G12: =F12 -> 52524.01 | H12: =ROUND((G12/$G$31),5) -> 0.01316 | I12: =#REF! -> #REF! | J12: =K12-I12 -> #REF! | K12: =(10/210)*G12 -> 2501.1433 | L12: =ROUND(K12/$G$31,5) -> 0.00063 | M12: =IF(L12=H12,"COMPLETED",IF(L12=0,"Not Yet Started","On going")) -> On going | N12: =(J12/G12)*D12 -> #REF! | P12: Length | Q12: Width | R12: Thickness | S12: Qty | T12: Volume | U12: Unit
A13: B.9 | B13: Mobilization/ Demobilization | D13: 1 | E13: l.s | F13: 31020.38 | G13: =F13 -> 31020.38 | H13: =ROUND((G13/$G$31),5) -> 0.00777 | I13: =#REF! -> #REF! | J13: =K13-I13 -> #REF! | K13: =0.5*G13 -> 15510.19 | L13: =ROUND(K13/$G$31,5) -> 0.00389 | M13: =IF(L13=H13,"COMPLETED",IF(L13=0,"Not Yet Started","On going")) -> On going | N13: =(J13/G13)*D13 -> #REF! | P13: 1.5 | Q13: 1.5 | R13: 0.1 | T13: =P13*Q13*R13*S13 -> 0 | U13: =E19 -> cu.m
A14: II | B14: WORK ITEMS
A15: 802 | B15: Excavation | D15: 92.65 | E15: cu.m | F15: 221.94 | G15: =ROUND(F15*D15,2) -> 20562.74 | H15: =ROUND((G15/$G$31),5) -> 0.00515 | I15: =#REF! -> #REF! | J15: =T9*F15 -> 2996.19 | K15: =G15*0.4 -> 8225.096 | L15: =ROUND(K15/$G$31,5) -> 0.00206 | M15: =IF(L15=H15,"COMPLETED",IF(L15=0,"Not Yet Started","On going")) -> On going | N15: =(J15/G15)*D15 -> 13.500001 | P15: 900 (a) | Q15: Reinforced Concrete Column Footing
A16: 804(a) | B16: Backfilling | D16: 32.4 | E16: cu.m | F16: 55.17 | G16: =ROUND(F16*D16,2) -> 1787.51 | H16: =ROUND((G16/$G$31),5) -> 0.00045 | I16: =#REF! -> #REF! | J16: =K16-I16 -> #REF! | K16: 0 | L16: =ROUND(K16/$G$31,5) -> 0 | M16: =IF(L16=H16,"COMPLETED",IF(L16=0,"Not Yet Started","On going")) -> Not Yet Started | N16: =(J16/G16)*D16 -> #REF! | P16: Length | Q16: Width | R16: Thickness | S16: Qty | T16: Volume | U16: Unit
A17: 804(b) | B17: Gravel Bedding | D17: 54.66 | E17: cu.m | F17: 813.59 | G17: =ROUND(F17*D17,2) -> 44470.83 | H17: =ROUND((G17/$G$31),5) -> 0.01114 | I17: =#REF! -> #REF! | J17: =T13*F17 -> 0 | L17: =ROUND(K17/$G$31,5) -> 0 | M17: =IF(L17=H17,"COMPLETED",IF(L17=0,"Not Yet Started","On going")) -> Not Yet Started | N17: =(J17/G17)*D17 -> 0 | P17: 1.5 | Q17: 1.5 | R17: 0.35 | T17: =P17*Q17*R17*S17 -> 0 | U17: =E23 -> sq.m.
A18: 900 (a) | B18: Reinforced Concrete Column Footing | D18: 9.45 | E18: cu.m | F18: 16311.68 | G18: =ROUND(F18*D18,2) -> 154145.38 | H18: =ROUND((G18/$G$31),5) -> 0.03862 | I18: =#REF! -> #REF! | J18: =T17*F18 -> 0 | L18: =ROUND(K18/$G$31,5) -> 0 | M18: =IF(L18=H18,"COMPLETED",IF(L18=0,"Not Yet Started","On going")) -> Not Yet Started | N18: =(J18/G18)*D18 -> 0
A19: 901 (b) | B19: Reinforced Concrete Wall Footing | D19: 3.12 | E19: cu.m | F19: 17371.06 | G19: =ROUND(F19*D19,2) -> 54197.71 | H19: =ROUND((G19/$G$31),5) -> 0.01358 | I19: =#REF! -> #REF! | J19: =K19-I19 -> #REF! | K19: 0 | L19: =ROUND(K19/$G$31,5) -> 0 | M19: =IF(L19=H19,"COMPLETED",IF(L19=0,"Not Yet Started","On going")) -> Not Yet Started | N19: =(J19/G19)*D19 -> #REF!
A20: 902 (c) | B20: Reinforced Concrete Column and Corbel | D20: 16.32 | E20: cu.m | F20: 22958.55 | G20: =ROUND(F20*D20,2) -> 374683.54 | H20: =ROUND((G20/$G$31),5) -> 0.09389 | I20: =#REF! -> #REF! | J20: =K20-I20 -> #REF! | K20: 0 | L20: =ROUND(K20/$G$31,5) -> 0 | M20: =IF(L20=H20,"COMPLETED",IF(L20=0,"Not Yet Started","On going")) -> Not Yet Started | N20: =(J20/G20)*D20 -> #REF!
A21: 903 (d) | B21: Reinforced Concrete Beams | D21: 5.6 | E21: cu.m | F21: 26671.53 | G21: =ROUND(F21*D21,2) -> 149360.57 | H21: =ROUND((G21/$G$31),5) -> 0.03743 | I21: =#REF! -> #REF! | J21: =K21-I21 -> #REF! | K21: 0 | L21: =ROUND(K21/$G$31,5) -> 0 | M21: =IF(L21=H21,"COMPLETED",IF(L21=0,"Not Yet Started","On going")) -> Not Yet Started | N21: =(J21/G21)*D21 -> #REF!
A22: 904 (e) | B22: Reinforced Concrete Slab | D22: 50.4 | E22: cu.m | F22: 9441 | G22: =ROUND(F22*D22,2) -> 475826.4 | H22: =ROUND((G22/$G$31),5) -> 0.11923 | I22: =#REF! -> #REF! | J22: =K22-I22 -> #REF! | K22: 0 | L22: =ROUND(K22/$G$31,5) -> 0 | M22: =IF(L22=H22,"COMPLETED",IF(L22=0,"Not Yet Started","On going")) -> Not Yet Started | N22: =(J22/G22)*D22 -> #REF!
A23: 903 | B23: Formworks and Falseworks | D23: 108 | E23: sq.m. | F23: 3583.04 | G23: =ROUND(F23*D23,2) -> 386968.32 | H23: =ROUND((G23/$G$31),5) -> 0.09696 | I23: =#REF! -> #REF! | J23: =K23-I23 -> #REF! | L23: =ROUND(K23/$G$31,5) -> 0 | M23: =IF(L23=H23,"COMPLETED",IF(L23=0,"Not Yet Started","On going")) -> Not Yet Started | N23: =(J23/G23)*D23 -> #REF!
A24: 1046 | B24: Masonry Works | D24: 36.8 | E24: sq.m. | F24: 968.36 | G24: =ROUND(F24*D24,2) -> 35635.65 | H24: =ROUND((G24/$G$31),5) -> 0.00893 | I24: =#REF! -> #REF! | J24: =K24-I24 -> #REF! | L24: =ROUND(K24/$G$31,5) -> 0 | M24: =IF(L24=H24,"COMPLETED",IF(L24=0,"Not Yet Started","On going")) -> Not Yet Started | N24: =(J24/G24)*D24 -> #REF!
A25: 1027 | B25: Cement Plaster Finish | D25: 212.76 | E25: sq.m. | F25: 55.61 | G25: =ROUND(F25*D25,2) -> 11831.58 | H25: =ROUND((G25/$G$31),5) -> 0.00296 | I25: =#REF! -> #REF! | J25: =K25-I25 -> #REF! | L25: =ROUND(K25/$G$31,5) -> 0 | M25: =IF(L25=H25,"COMPLETED",IF(L25=0,"Not Yet Started","On going")) -> Not Yet Started | N25: =(J25/G25)*D25 -> #REF!
A26: 1032 | B26: Painting Works | D26: 194.36 | E26: sq.m. | F26: 358.8 | G26: =ROUND(F26*D26,2) -> 69736.37 | H26: =ROUND((G26/$G$31),5) -> 0.01747 | I26: =#REF! -> #REF! | J26: =K26-I26 -> #REF! | K26: 0 | L26: =ROUND(K26/$G$31,5) -> 0 | M26: =IF(L26=H26,"COMPLETED",IF(L26=0,"Not Yet Started","On going")) -> Not Yet Started | N26: =(J26/G26)*D26 -> #REF!
A27: 1047 | B27: Metal Structure | D27: 16113.92 | E27: kgs. | F27: 90.41 | G27: =ROUND(F27*D27,2) -> 1456859.5 | H27: =ROUND((G27/$G$31),5) -> 0.36505 | I27: =#REF! -> #REF! | J27: =K27-I27 -> #REF! | L27: =ROUND(K27/$G$31,5) -> 0 | M27: =IF(L27=H27,"COMPLETED",IF(L27=0,"Not Yet Started","On going")) -> Not Yet Started | N27: =(J27/G27)*D27 -> #REF!
A28: 1013(a) | B28: Corrugated Asphalt Roof | D28: 684 | E28: sq.m. | F28: 793.5 | G28: =ROUND(F28*D28,2) -> 542754 | H28: =ROUND((G28/$G$31),5) -> 0.136 | I28: =#REF! -> #REF! | J28: =K28-I28 -> #REF! | K28: 0 | L28: =ROUND(K28/$G$31,5) -> 0 | M28: =IF(L28=H28,"COMPLETED",IF(L28=0,"Not Yet Started","On going")) -> Not Yet Started | N28: =(J28/G28)*D28 -> #REF!
A29: 1103 | B29: Electrical Works | D29: 12 | E29: units | F29: 8231.21 | G29: =ROUND(F29*D29,2) -> 98774.52 | H29: =ROUND((G29/$G$31),5) -> 0.02475 | I29: =#REF! -> #REF! | J29: =K29-I29 -> #REF! | L29: =ROUND(K29/$G$31,5) -> 0 | M29: =IF(L29=H29,"COMPLETED",IF(L29=0,"Not Yet Started","On going")) -> Not Yet Started | N29: =(J29/G29)*D29 -> #REF!
A31: T O T A L S | G31: =SUM(G10:G30) -> 3990837.4 | H31: =SUM(H10:H29) -> 0.99998 | J31: =SUM(J10:J30) -> #REF! | K31: =SUM(K10:K30) -> 26236.429 | L31: =SUM(L10:L29) -> 0.00658
F34: % THIS ACCOMPLISHMENT | I34: =L31 -> 0.00658
F35: TOTAL PROJECT COST | I35: =G31 -> 3990837.4
F36: TOTAL THIS ACCOMPLISHMENT | I36: =J31 -> #REF!
E37: Less: | F37: MOBILIZATION
F38: TOTAL THIS VOUCHER | I38: =SUM(J31-I37) -> #REF!
A40: Prepared by: | C40: Checked by: | G40: Recommending Approval: | K40: Approved:
A44: MARK KEVIN B. MARTIN | C44: KATHLEEN MEI P. BAGASIN | G44: KINGSTON JAMES S. DELA CRUZ | K44: MANUEL N. MAMBA, M.D.
A45: Engineer II | C45: Chief of Construction Division | G45: Provincial Engineer | K45: Governor
B47: =B1 -> STATEMENT OF WORK ACCOMPLISHMENT
B48: As of _____________________, 2020
A50: A. | B50: ='[2]SWA(abd)'!B12 -> CONCRETING OF FARM TO MARKET ROAD ZIMINILA
B51: ='[2]SWA(abd)'!B13 -> CAMALANIUGAN, CAGAYAN
A53: ITEM | B53: DESCRIPTION OF WORK | D53: PROGRAMMED | F53: UNIT | G53: CONTRACT | H53: WEIGHT | I53: ACCOMPLISHMENT | L53: WEIGHT | M53: REMARKS/
A54: NO. | D54: QUANTITY | F54: PRICE | G54: AMOUNT | H54: % | I54: PREVIOUS | J54: THIS PERIOD | K54: TO DATE | L54: % | M54: STATUS
D55: ORIGINAL | R55: 0.16
A56: ='[2]SWA(abd)'!A17 -> 105(1) | B56: ='[2]SWA(abd)'!B17:C17 -> Sub Grade Preparation | D56: ='[2]SWA(abd)'!D17 -> 1075.8 | E56: ='[2]SWA(abd)'!E17 -> sq.m. | F56: ='[2]SWA(abd)'!F17 -> 102.17 | G56: ='[2]SWA(abd)'!G17 -> 109364.91 | H56: =(G56/$G$63)*100 -> 10.022838 | K56: =I56+J56 -> 0 | L56: =ROUND(K56/#REF!,4) -> #REF! | M56: on-going | Q56: =D56*F56 -> 109914.49 | R56: =Q56*$R$55 -> 17586.318 | S56: =Q56-R56 -> 92328.168
A57: ='[2]SWA(abd)'!A18 -> 200(1) | B57: ='[2]SWA(abd)'!B18:C18 -> Aggregate Sub Base Coarse | D57: ='[2]SWA(abd)'!D18 -> 173.25 | E57: ='[2]SWA(abd)'!E18 -> sq.m. | F57: 804.58 | G57: ='[2]SWA(abd)'!G18 -> 223636.89 | H57: =(G57/$G$63)*100 -> 20.495388 | K57: =I57+J57 -> 0 | L57: =ROUND(K57/$G$63,4) -> 0 | M57: on-going | Q57: =D57*F57 -> 139393.49 | R57: =Q57*$R$55 -> 22302.958 | S57: =Q57-R57 -> 117090.53
A58: ='[2]SWA(abd)'!A19 -> 311(1)C | B58: ='[2]SWA(abd)'!B19:C19 -> PCCP | D58: ='[2]SWA(abd)'!D19 -> 660 | E58: ='[2]SWA(abd)'!E19 -> sq.m. | F58: 72.96 | G58: ='[2]SWA(abd)'!G19 -> 672973.03 | H58: =(G58/$G$63)*100 -> 61.675171 | K58: =I58+J58 -> 0 | L58: =ROUND(K58/$G$63,4) -> 0 | M58: on-going | O58: =0.2*#REF! -> #REF! | P58: =0.95*#REF! -> #REF! | Q58: =D58*F58 -> 48153.6 | R58: =Q58*$R$55 -> 7704.576 | S58: =Q58-R58 -> 40449.024
A59: ='[2]SWA(abd)'!A20 -> B.9 | B59: ='[2]SWA(abd)'!B20:C20 -> Mobilization/ Demobilization | D59: ='[2]SWA(abd)'!D20 -> 1 | E59: ='[2]SWA(abd)'!E20 -> l/s | F59: 128.93 | G59: ='[2]SWA(abd)'!G20 -> 25951.88 | H59: =(G59/$G$63)*100 -> 2.3783815 | K59: =I59+J59 -> 0 | L59: =ROUND(K59/$G$63,4) -> 0 | M59: on-going | O59: 604.87 | P59: =0.95*#REF! -> #REF! | Q59: =D59*F59 -> 128.93 | R59: =Q59*$R$55 -> 20.6288 | S59: =Q59-R59 -> 108.3012
A60: ='[2]SWA(abd)'!A21 -> B.5 | B60: ='[2]SWA(abd)'!B21:C21 -> Billboards and Signages | D60: ='[2]SWA(abd)'!D21 -> 2 | E60: ='[2]SWA(abd)'!E21 -> each | F60: 18.37 | G60: ='[2]SWA(abd)'!G21 -> 10196.76 | H60: =(G60/$G$63)*100 -> 0.93449052 | K60: =I60+J60 -> 0 | L60: =ROUND(K60/$G$63,4) -> 0 | M60: on-going | O60: =0.2*#REF! -> #REF! | P60: =0.95*#REF! -> #REF! | Q60: =D60*F60 -> 36.74 | R60: =Q60*$R$55 -> 5.8784 | S60: =Q60-R60 -> 30.8616
A61: ='[2]SWA(abd)'!A22 -> B.7 | B61: ='[2]SWA(abd)'!B22:C22 -> Occupational Health and Safety | D61: ='[2]SWA(abd)'!D22 -> 1 | E61: ='[2]SWA(abd)'!E22 -> l/s | F61: 1208.89 | G61: ='[2]SWA(abd)'!G22 -> 28041.09 | H61: =(G61/$G$63)*100 -> 2.5698489 | K61: =I61+J61 -> 0 | L61: =ROUND(K61/$G$63,4) -> 0 | M61: on-going | O61: =0.2*#REF! -> #REF! | P61: =0.9*#REF! -> #REF! | Q61: =D61*F61 -> 1208.89 | R61: =Q61*$R$55 -> 193.4224 | S61: =Q61-R61 -> 1015.4676
A62: ='[2]SWA(abd)'!A23 -> A.1.1(8a) | B62: ='[2]SWA(abd)'!B23:C23 -> Provisions of Field Office for the Engineer | D62: ='[2]SWA(abd)'!D23 -> 1.83 | E62: ='[2]SWA(abd)'!E23 -> mos | F62: 1291.19 | G62: ='[2]SWA(abd)'!G23 -> 20992.58 | H62: =(G62/$G$63)*100 -> 1.9238824 | K62: =I62+J62 -> 0 | L62: =ROUND(K62/$G$63,4) -> 0 | M62: on-going | O62: =350*3.05 -> 1067.5 | Q62: =D62*F62 -> 2362.8777 | R62: =Q62*$R$55 -> 378.06043 | S62: =Q62-R62 -> 1984.8173
A63: T O T A L S | G63: =SUM(G56:G62) -> 1091157.1 | H63: =SUM(H56:H62) -> 100 | I63: =SUM(I56:I62) -> 0 | J63: =SUM(J56:J62) -> 0 | K63: =SUM(K56:K62) -> 0 | L63: =SUM(L56:L62) -> #REF! | Q63: =SUM(Q56:Q62) -> 301199.01 | R63: =SUM(R56:R62) -> 48191.841 | S63: =SUM(S56:S62) -> 253007.17
O64: =0.85*#REF! -> #REF! | Q64: =Q63*0.0065 -> 1957.7936
Q65: =Q63-Q64 -> 299241.22
F66: % THIS ACCOMPLISHMENT | I66: =L63*100 -> #REF! | K66: %
F67: TOTAL PROJECT COST | I67: =ROUND(G63,2) -> 1091157.1
F68: TOTAL THIS ACCOMPLISHMENT | I68: =J63 -> 0
E69: Less: | F69: MOBILIZATION
F70: TOTAL THIS VOUCHER | I70: =SUM(J63-I69) -> 0
A72: Requested by: | C72: Prepared by: | F72: Checked by: | J72: Approved:
A76: EV INTERIOR CONSTRUCTION | C76: MARISSA A. MACADANGDANG | F76: MA. VICTORIA E. REYES | J76: MANUEL N. MAMBA, M.D.
A77: Contractor | C77: Engineering Assistant | F77: Engineer II | J77: Governor

Sheet STEWA (August 30, 2024)
A2: Republic of the Philippines
A3: PROVINCE OF CAGAYAN
A4: Capitol Hills, Tuguegarao City
A5: PROVINCIAL ENGINEER'S OFFICE
H6: JUST FILL IN ON BLUE CELL!!! | M6: LEGEND:
A7: STATEMENT OF TIME ELAPSED AND WORK ACCOMPLISHED | M7: single | N7: WITHOUT REVISION
M8: in a relationship | N8: WITH REVISION
B9: =I9 -> 45534 | H9: To be Filled In | I9: 45534 | M9: complicated | N9: ON THE EXPIRY DATE WITHOUT REVISION
M10: married | N10: ON THE EXPIRY DATE WITH REVISION
M11: separated | N11: ON THE COMPLETION DATE WITHOUT REVISION
A12: Project Name | C12: : | D12: =I12 -> Construction of Multi-Purpose Building Lallo National High School | H12: To be Filled In | I12: Construction of Multi-Purpose Building Lallo National High School | J12: Project Name | M12: divorced | N12: ON THE COMPLETION DATE WITH REVISION
A13: Location | C13: : | D13: =I13 -> Lallo, Cagayan | H13: To be Filled In | I13: Lallo, Cagayan | J13: Location | M13: LDR_1 | N13: WITHOUT REVISION
A14: Contract Amount | C14: : | D14: =I14 -> 3796932.5 | H14: To be Filled In | I14: 3796932.5 | J14: Contract Amount | M14: LDR_2 | N14: WITH REVISION
A15: Contractor | C15: : | D15: =I15 -> Rucs Konsult and Construction Services | H15: To be Filled In | I15: Rucs Konsult and Construction Services | J15: Contractor
A17: 1. | B17: Period Covered: | C17: : | D17: =D20+9 -> 45045 | E17: to
D18: =+B9 -> 45534
A19: 2. | B19: Contract Duration | C19: : | D19: =I19 -> 180 | H19: To be Filled In | I19: 180 | J19: Contract Duration
A20: 3. | B20: Date of Receipt of Notice to Proceed | C20: : | D20: =I20 -> 45036 | H20: To be Filled In | I20: 45036 | J20: Date of Receipt of Notice to Proceed
A21: 4. | B21: Expiry Date | C21: : | D21: =+D17+D19 -> 45225
A22: 5. | B22: Approved Time Extension | C22: : | D22: =I22 -> 0 | H22: To be Filled In | J22: Approved Time Extension
A23: 6. | B23: Approved Time Suspension | C23: : | D23: =I23 -> 446 | H23: To be Filled In | I23: 446 | J23: Approved Time Suspension
A24: 7. | B24: Total Time Extension | D24: =IF(I24>0,I24,0) -> 0 | H24: Don't Fill In | I24: =D22 -> 0 | J24: Total Time Extension
A25: 8. | B25: Revised Contract Duration | C25: : | D25: =IF(I24>0,I25,0) -> 0 | H25: Don't Fill In | I25: =IF(D22>0,D22+I19,0)-1 -> -1 | J25: Revised Contract Duration
A26: 9. | B26: Revised Expiry Date | C26: : | D26: =D21+D23 -> 45671
A27: 10. | B27: Total Calendar days Elapsed to Date | C27: : | D27: =+D18-D17+1-D23 -> 44
A28: 11. | B28: Percentage of work accomplished - Actual | C28: : | D28: =#REF! -> #REF! | I28: ='SWA (August 30, 2024)'!L31 -> 0.00658 | J28: (FROM SWA)
A29: 12. | B29: Percentage of work accomplished -Planned | C29: : | D29: =I29 -> 0.1403301 | H29: Don't Fill In | I29: =(((SIN((((180*((D27))/D19)-90)*(3.14159265358979/180)))+1)*50)/100) -> 0.1403301 | J29: W/ FORMULA - Planned (WITHOUT time extension)
A30: 13. | B30: Slippage | C30: : | D30: =D28-D29 -> #REF! | H30: Don't Fill In | I30: =IF(I25>0,(((SIN((((180*((D27))/D25)-90)*(3.14159265358979/180)))+1)*50)/100),"") | J30: W/ FORMULA - Planned (WITH time extension)
A31: 14. | B31: Remarks | C31: :
H32: Don't Fill In | I32: =D27/D19 -> 0.24444444 | J32: LINEAR - Planned (WITHOUT time extension)
H33: Don't Fill In | I33: 1 | J33: LINEAR - Planned (WITH time extension)
B35: Submitted by: | D35: Noted by: | H35: F | I35: WRITE "F" - OPT TO USE FORMULA
I36: WRITE "L" - OPT TO USE LINEAR
B38: MARK KEVIN B. MARTIN | D38: KATHLEEN MEI P. BAGASIN
B39: Engineer II | D39: Engineer IV (Chief-Construction Division)

Sheet swa_BC
A1: STATEMENT OF WORK ACCOMPLISHMENT
B4: Improvement of Road along Sta. Cruz - Cabiraoan Provincial Road - Concreting of Road with Box Culvert
B5: Gonzaga, Cagayan
A7: ITEM | B7: DESCRIPTION OF WORK | D7: PROGRAMMED | F7: UNIT | G7: CONTRACT | H7: WEIGHT | I7: ACCOMPLISHMENT | L7: WEIGHT | M7: REMARKS/
A8: NO. | D8: QUANTITY | F8: PRICE | G8: AMOUNT | H8: % | I8: PREVIOUS | J8: THIS PERIOD | K8: TO DATE | L8: % | M8: STATUS
D9: ORIGINAL | P9: 497476.03
B10: Project Billboard | D10: 230 | E10: sq.m | F10: 50.74 | G10: =ROUND(F10*D10,2) -> 11670.2 | H10: =ROUND((G10/$G$30),5) -> 0.01185 | J10: =G10 -> 11670.2 | K10: =J10 -> 11670.2 | L10: =ROUND(K10/$G$30,5) -> 0.01185 | M10: =IF(G10=K10,IF(G10>0,"COMPLETED","Removed"),"On-going") -> COMPLETED | O10: 0.0142 | P10: =ROUND($P$9*O10,3) -> 7064.16 | Q10: =ROUND(P10/D10,5) -> 30.71374 | R10: =ROUND(Q10*D10,2) -> 7064.16
B11: Construction Safety and Health Program | D11: 46 | E11: cu.m | F11: 979.58 | G11: =ROUND(F11*D11,2) -> 45060.68 | H11: =ROUND((G11/$G$30),5) -> 0.04575 | J11: =G11 -> 45060.68 | K11: =J11 -> 45060.68 | L11: =ROUND(K11/$G$30,5) -> 0.04575 | M11: =IF(G11=K11,IF(G11>0,"COMPLETED","Removed"),"On-going") -> COMPLETED | O11: 0.0142 | P11: =ROUND($P$9*O11,3) -> 7064.16 | Q11: =ROUND(P11/D11,5) -> 153.5687 | R11: =ROUND(Q11*D11,2) -> 7064.16
B12: Mobilization/ Demobilization | D12: 230 | E12: sq.m | F12: 1360.32 | G12: =ROUND(F12*D12,2) -> 312873.6 | H12: =ROUND((G12/$G$30),5) -> 0.31765 | J12: =G12 -> 312873.6 | K12: =J12 -> 312873.6 | L12: =ROUND(K12/$G$30,5) -> 0.31765 | M12: =IF(G12=K12,IF(G12>0,"COMPLETED","Removed"),"On-going") -> COMPLETED | O12: 0.6423 | P12: =ROUND($P$9*O12,3) -> 319528.85 | Q12: =ROUND(P12/D12,5) -> 1389.2559 | R12: =ROUND(Q12*D12,2) -> 319528.85
B13: Removal of Existing Concrete Pavement | D13: 64.8 | E13: cu.m | F13: 169.17 | G13: =ROUND(F13*D13,2) -> 10962.22 | H13: =ROUND((G13/$G$30),5) -> 0.01113 | J13: =G13 -> 10962.22 | K13: =J13 -> 10962.22 | L13: =ROUND(K13/$G$30,5) -> 0.01113 | M13: =IF(G13=K13,IF(G13>0,"COMPLETED","Removed"),"On-going") -> COMPLETED | O13: 0.2857 | P13: =ROUND($P$9*O13,3) -> 142128.9 | Q13: =ROUND(P13/D13,5) -> 2193.3472 | R13: =ROUND(Q13*D13,2) -> 142128.9
B14: Removal of Actual Structures/Obstruction (610mmØ RCPC) | D14: 3021.44 | E14: kg | F14: 76.22 | G14: =ROUND(F14*D14,2) -> 230294.16 | H14: =ROUND((G14/$G$30),5) -> 0.23381 | J14: =G14 -> 230294.16 | K14: =J14 -> 230294.16 | L14: =ROUND(K14/$G$30,5) -> 0.23381 | M14: =IF(G14=K14,IF(G14>0,"COMPLETED","Removed"),"On-going") -> COMPLETED | O14: 0.0254 | P14: =ROUND($P$9*O14,3) -> 12635.891 | Q14: =ROUND(P14/D14,5) -> 4.18208 | R14: =ROUND(Q14*D14,2) -> 12635.9
B15: Roadway Excavation (Surplus Common Excavation) | D15: 36 | E15: cu.m | F15: 7119 | G15: =ROUND(F15*D15,2) -> 256284 | H15: =ROUND((G15/$G$30),5) -> 0.2602 | J15: =G15 -> 256284 | K15: =J15 -> 256284 | L15: =ROUND(K15/$G$30,5) -> 0.2602 | M15: =IF(G15=K15,IF(G15>0,"COMPLETED","Removed"),"On-going") -> COMPLETED | O15: 0.0103 | P15: =ROUND($P$9*O15,3) -> 5124.003 | Q15: =ROUND(P15/D15,5) -> 142.33342 | R15: =ROUND(Q15*D15,2) -> 5124
B16: Structure Excavation | D16: 46 | E16: ln.m | F16: 1607.18 | G16: =ROUND(F16*D16,2) -> 73930.28 | H16: =ROUND((G16/$G$30),5) -> 0.07506 | J16: =G16 -> 73930.28 | K16: =J16 -> 73930.28 | L16: =ROUND(K16/$G$30,5) -> 0.07506 | M16: =IF(G16=K16,IF(G16>0,"COMPLETED","Removed"),"On-going") -> COMPLETED | O16: 0.0079 | P16: =ROUND($P$9*O16,3) -> 3930.061 | Q16: =ROUND(P16/D16,5) -> 85.43611 | R16: =ROUND(Q16*D16,2) -> 3930.06
B17: Pipe Culvert and Drain Excavation | D17: 1 | E17: ls | F17: 6825 | G17: =ROUND(F17*D17,2) -> 6825 | H17: =ROUND((G17/$G$30),5) -> 0.00693 | J17: =G17 -> 6825 | K17: =J17 -> 6825 | L17: =ROUND(K17/$G$30,5) -> 0.00693 | M17: =IF(G17=K17,IF(G17>0,"COMPLETED","Removed"),"On-going") -> COMPLETED | O17: 0.0254 | P17: =ROUND($P$9*O17,3) -> 12635.891 | Q17: =ROUND(P17/D17,5) -> 12635.891 | R17: =ROUND(Q17*D17,2) -> 12635.89
B18: Embankment (From Roadway Excavation) | D18: 1 | E18: ls | F18: 12726 | G18: =ROUND(F18*D18,2) -> 12726 | H18: =ROUND((G18/$G$30),5) -> 0.01292 | J18: =G18 -> 12726 | K18: =J18 -> 12726 | L18: =ROUND(K18/$G$30,5) -> 0.01292 | M18: =IF(G18=K18,IF(G18>0,"COMPLETED","Removed"),"On-going") -> COMPLETED | O18: 0.0103 | P18: =ROUND($P$9*O18,3) -> 5124.003 | Q18: =ROUND(P18/D18,5) -> 5124.003 | R18: =ROUND(Q18*D18,2) -> 5124
B19: Sub-grade Preparation (Common Materials) | D19: 2.5 | E19: mos | F19: 5197.5 | G19: =ROUND(F19*D19,2) -> 12993.75 | H19: =ROUND((G19/$G$30),5) -> 0.01319 | J19: =G19 -> 12993.75 | K19: =J19 -> 12993.75 | L19: =ROUND(K19/$G$30,5) -> 0.01319 | M19: =IF(G19=K19,IF(G19>0,"COMPLETED","Removed"),"On-going") -> COMPLETED | O19: 0.0079 | P19: =ROUND($P$9*O19,3) -> 3930.061 | Q19: =ROUND(P19/D19,5) -> 1572.0244 | R19: =ROUND(Q19*D19,2) -> 3930.06
B20: Aggregate Sub-base Course | D20: 2 | E20: each | F20: 5670 | G20: =ROUND(F20*D20,2) -> 11340 | H20: =ROUND((G20/$G$30),5) -> 0.01151 | J20: =G20 -> 11340 | K20: =J20 -> 11340 | L20: =ROUND(K20/$G$30,5) -> 0.01151 | M20: =IF(G20=K20,IF(G20>0,"COMPLETED","Removed"),"On-going") -> COMPLETED | O20: =SUM(O10:O16) -> 1 | P20: =SUM(P10:P16) -> 497476.03 | R20: =SUM(R10:R16) -> 497476.03
B21: Portland Cement Concrete Pavement, 230mm thk.
B22: Reinforcing Steel (Line Drainage
A30: T O T A L S | G30: =SUM(G10:G21) -> 984959.89 | H30: =SUM(H10:H21) -> 1 | I30: =SUM(I10:I29) -> 0 | J30: =ROUND(SUM(J10:J29),2) -> 984959.89 | K30: =ROUND(SUM(K10:K29),2) -> 984959.89 | L30: =SUM(L10:L29) -> 1
F33: % THIS ACCOMPLISHMENT | J33: =L30 -> 1
F34: TOTAL PROJECT COST | J34: =G30 -> 984959.89
F35: TOTAL THIS ACCOMPLISHMENT | J35: =J30 -> 984959.89
E36: Less:
F37: TOTAL THIS VOUCHER | J37: =SUM(K30-J36) -> 984959.89
A39: Requested by: | C39: Prepared by: | F39: Checked and Reviewed by: | I39: Submitted by: | L39: Approved:
C43: MA. VICTORIA E. REYES | F43: ARNOLD L. MANUEL | I43: =$I$43 -> VINCENT S. TAGUBA | L43: MANUEL N. MAMBA, M.D.
A44: Contractor | C44: Engineer II | F44: OIC- Chief of Construction Division | I44: =$I$44 -> Asst. Provincial Engineer- Designate | L44: Governor
A45: Requested by: | C45: Prepared by: | F45: Checked by: | J45: Submitted by: | N45: Approved:
A49: =#REF! -> #REF! | C49: MARISSA A. MACADANGDANG | F49: MA. VICTORIA E. REYES | J49: ='[2]SWA(abd)'!H134 -> VINCENT S. TAGUBA | N49: MANUEL N. MAMBA, M.D.
A50: Contractor | C50: Engineering Assistant | F50: Engineer II | J50: ='[2]SWA(abd)'!H135 -> Asst. Provincial Engineer- Designate | N50: Governor
B52: =A1 -> STATEMENT OF WORK ACCOMPLISHMENT
B53: As of _____________________, 2020
A55: A. | B55: ='[2]SWA(abd)'!B12 -> CONCRETING OF FARM TO MARKET ROAD ZIMINILA
B56: ='[2]SWA(abd)'!B13 -> CAMALANIUGAN, CAGAYAN
A58: ITEM | B58: DESCRIPTION OF WORK | D58: PROGRAMMED | F58: UNIT | G58: CONTRACT | H58: WEIGHT | I58: PROGRAMMED | K58: UNIT | L58: CONTRACT | M58: ACCOMPLISHMENT | P58: WEIGHT | Q58: REMARKS/
A59: NO. | D59: QUANTITY | F59: PRICE | G59: AMOUNT | H59: % | I59: QUANTITY | K59: PRICE | L59: AMOUNT | M59: PREVIOUS | N59: THIS PERIOD | O59: TO DATE | P59: % | Q59: STATUS
D60: ORIGINAL | I60: VARIATION ORDER NO.1
A61: ='[2]SWA(abd)'!A17 -> 105(1) | B61: ='[2]SWA(abd)'!B17:C17 -> Sub Grade Preparation | D61: ='[2]SWA(abd)'!D17 -> 1075.8 | E61: ='[2]SWA(abd)'!E17 -> sq.m. | F61: ='[2]SWA(abd)'!F17 -> 102.17 | G61: ='[2]SWA(abd)'!G17 -> 109364.91 | H61: =(G61/$G$68)*100 -> 10.022838 | I61: =[2]vo1_A!K13 -> 1075.8 | J61: Each | K61: =[2]vo1_A!D13 -> 102.17 | L61: =ROUND(I61*K61*0.995,2) -> 109364.91 | O61: =M61+N61 -> 0 | P61: =ROUND(O61/$L$68,4) -> 0 | Q61: on-going
A62: ='[2]SWA(abd)'!A18 -> 200(1) | B62: ='[2]SWA(abd)'!B18:C18 -> Aggregate Sub Base Coarse | D62: ='[2]SWA(abd)'!D18 -> 173.25 | E62: ='[2]SWA(abd)'!E18 -> sq.m. | F62: 804.58 | G62: ='[2]SWA(abd)'!G18 -> 223636.89 | H62: =(G62/$G$68)*100 -> 20.495388 | I62: =[2]vo1_A!K14 -> 173.25 | J62: Each | K62: =[2]vo1_A!D14 -> 1297.32 | L62: =ROUND(I62*K62*0.995,2) -> 223636.89 | O62: =M62+N62 -> 0 | P62: =ROUND(O62/$G$68,4) -> 0 | Q62: on-going
A63: ='[2]SWA(abd)'!A19 -> 311(1)C | B63: ='[2]SWA(abd)'!B19:C19 -> PCCP | D63: ='[2]SWA(abd)'!D19 -> 660 | E63: ='[2]SWA(abd)'!E19 -> sq.m. | F63: 72.96 | G63: ='[2]SWA(abd)'!G19 -> 672973.03 | H63: =(G63/$G$68)*100 -> 61.675171 | I63: =[2]vo1_A!K15 -> 660 | J63: cu.m. | K63: =[2]vo1_A!D15 -> 1024.78 | L63: =ROUND(I63*K63*0.995,2) -> 672973.03 | O63: =M63+N63 -> 0 | P63: =ROUND(O63/$G$68,4) -> 0 | Q63: on-going
A64: ='[2]SWA(abd)'!A20 -> B.9 | B64: ='[2]SWA(abd)'!B20:C20 -> Mobilization/ Demobilization | D64: ='[2]SWA(abd)'!D20 -> 1 | E64: ='[2]SWA(abd)'!E20 -> l/s | F64: 128.93 | G64: ='[2]SWA(abd)'!G20 -> 25951.88 | H64: =(G64/$G$68)*100 -> 2.3783815 | I64: =[2]vo1_A!K16 -> 1 | J64: cu.m. | K64: =[2]vo1_A!D16 -> 26082.29 | L64: =ROUND(I64*K64*0.995,2) -> 25951.88 | O64: =M64+N64 -> 0 | P64: =ROUND(O64/$G$68,4) -> 0 | Q64: on-going
A65: ='[2]SWA(abd)'!A21 -> B.5 | B65: ='[2]SWA(abd)'!B21:C21 -> Billboards and Signages | D65: ='[2]SWA(abd)'!D21 -> 2 | E65: ='[2]SWA(abd)'!E21 -> each | F65: 18.37 | G65: ='[2]SWA(abd)'!G21 -> 10196.76 | H65: =(G65/$G$68)*100 -> 0.93449052 | I65: =[2]vo1_A!K17 -> 2 | J65: sq.m. | K65: =[2]vo1_A!D17 -> 5124 | L65: =ROUND(I65*K65*0.995,2) -> 10196.76 | O65: =M65+N65 -> 0 | P65: =ROUND(O65/$G$68,4) -> 0 | Q65: on-going
A66: ='[2]SWA(abd)'!A22 -> B.7 | B66: ='[2]SWA(abd)'!B22:C22 -> Occupational Health and Safety | D66: ='[2]SWA(abd)'!D22 -> 1 | E66: ='[2]SWA(abd)'!E22 -> l/s | F66: 1208.89 | G66: ='[2]SWA(abd)'!G22 -> 28041.09 | H66: =(G66/$G$68)*100 -> 2.5698489 | I66: =[2]vo1_A!K18 -> 1 | J66: cu.m. | K66: =[2]vo1_A!D18 -> 28182 | L66: =ROUND(I66*K66*0.995,2) -> 28041.09 | O66: =M66+N66 -> 0 | P66: =ROUND(O66/$G$68,4) -> 0 | Q66: on-going
A67: ='[2]SWA(abd)'!A23 -> A.1.1(8a) | B67: ='[2]SWA(abd)'!B23:C23 -> Provisions of Field Office for the Engineer | D67: ='[2]SWA(abd)'!D23 -> 1.83 | E67: ='[2]SWA(abd)'!E23 -> mos | F67: 1291.19 | G67: ='[2]SWA(abd)'!G23 -> 20992.58 | H67: =(G67/$G$68)*100 -> 1.9238824 | I67: =[2]vo1_A!K19 -> 1.83 | J67: sq.m. | K67: =[2]vo1_A!D19 -> 11529 | L67: =ROUND(I67*K67*0.995,2) -> 20992.58 | O67: =M67+N67 -> 0 | P67: =ROUND(O67/$G$68,4) -> 0 | Q67: on-going
A68: T O T A L S | G68: =SUM(G61:G67) -> 1091157.1 | H68: =SUM(H61:H67) -> 100 | L68: =SUM(L61:L67) -> 1091157.1 | M68: =SUM(M61:M67) -> 0 | N68: =SUM(N61:N67) -> 0 | O68: =SUM(O61:O67) -> 0 | P68: =SUM(P61:P67) -> 0
F71: % THIS ACCOMPLISHMENT | M71: =P68*100 -> 0 | O71: % | V71: 0.16
F72: TOTAL PROJECT COST | M72: =ROUND(G68,2) -> 1091157.1 | U72: =D61*F61 -> 109914.49 | V72: =U72*$V$71 -> 17586.318 | W72: =U72-V72 -> 92328.168
F73: TOTAL THIS ACCOMPLISHMENT | M73: =N68 -> 0 | U73: =D62*F62 -> 139393.49 | V73: =U73*$V$71 -> 22302.958 | W73: =U73-V73 -> 117090.53
E74: Less: | F74: MOBILIZATION | S74: =0.2*I63 -> 132 | T74: =0.95*I63 -> 627 | U74: =D63*F63 -> 48153.6 | V74: =U74*$V$71 -> 7704.576 | W74: =U74-V74 -> 40449.024
F75: TOTAL THIS VOUCHER | M75: =SUM(N68-M74) -> 0 | S75: 604.87 | T75: =0.95*I64 -> 0.95 | U75: =D64*F64 -> 128.93 | V75: =U75*$V$71 -> 20.6288 | W75: =U75-V75 -> 108.3012
S76: =0.2*I65 -> 0.4 | T76: =0.95*I65 -> 1.9 | U76: =D65*F65 -> 36.74 | V76: =U76*$V$71 -> 5.8784 | W76: =U76-V76 -> 30.8616
A77: Requested by: | C77: Prepared by: | F77: Checked by: | J77: Submitted by: | N77: Approved: | S77: =0.2*I66 -> 0.2 | T77: =0.9*I66 -> 0.9 | U77: =D66*F66 -> 1208.89 | V77: =U77*$V$71 -> 193.4224 | W77: =U77-V77 -> 1015.4676
S78: =350*3.05 -> 1067.5 | U78: =D67*F67 -> 2362.8777 | V78: =U78*$V$71 -> 378.06043 | W78: =U78-V78 -> 1984.8173
U79: =SUM(U72:U78) -> 301199.01 | V79: =SUM(V72:V78) -> 48191.841 | W79: =SUM(W72:W78) -> 253007.17
S80: =0.85*#REF! -> #REF! | U80: =U79*0.0065 -> 1957.7936
A81: EV INTERIOR CONSTRUCTION | C81: MARISSA A. MACADANGDANG | F81: MA. VICTORIA E. REYES | J81: BASILIA B. FLORES | N81: MANUEL N. MAMBA, M.D. | U81: =U79-U80 -> 299241.22
A82: Contractor | C82: Engineering Assistant | F82: Engineer II | J82: Provincial Engineer | N82: Governor

Sheet 500(1)a3 (2)
A1: NAME OF PROJECT: | C1: =[3]ipw_!E8 -> Improvement of Road Network at Gattaran District Hospital
A2: ITEM No.: | C2: 500(1)a3 | F2: UNIT: | G2: ln.m.
A3: DESCRIPTION: | C3: Reiforced Concrete Pipe Culvert, 910mm Ø | F3: QUANTITY: | G3: 9
A5: 1. DIRECT COST | O5: Station Cover | Q5: Length (ln.m.)
A6: 1.a. | B6: Materials | N6: 1 | O6: 617.4305 | P6: proposed | Q6: 7
A7: Description | D7: Unit | E7: Quantity | F7: Unit Cost | G7: Amount | N7: 2 | O7: 758.7117 | P7: R&R
A8: RCPC, 610 mm. dia. | D8: pcs. | E8: =G3 -> 9 | F8: =[3]materials!F16 -> 1200 | G8: =ROUND(F8*E8,2) -> 10800 | N8: 3 | O8: 820.358 | P8: R&R
A9: Portland Cement | D9: bags. | E9: =$G$3*0.774 -> 6.966 | F9: =[3]materials!F5 -> 260 | G9: =ROUND(F9*E9,2) -> 1811.16 | N9: 4 | O9: 897.203 | P9: R&R
A10: Fine Aggregates | D10: cu.m. | E10: =$G$3*0.044 -> 0.396 | F10: =[3]aggregates_!H44 -> 555.28 | G10: =ROUND(F10*E10,2) -> 219.89 | N10: 5 | O10: 935.6437 | P10: R&R
A11: Coarse Aggregates | D11: cu.m. | E11: =$G$3*0.088 -> 0.792 | F11: =[3]aggregates_!H53 -> 588.78 | G11: =ROUND(F11*E11,2) -> 466.31 | N11: 6 | O11: 969.8518 | P11: R&R
F12: 1.a. Total Material Cost = | G12: =ROUND(SUM(G8:G11),2) -> 13297.36 | N12: 7 | O12: 1048.6413 | P12: R&R
N13: 8 | O13: 1286.1256 | P13: R&R | Q13: 8
A14: 1.b. | B14: Labor | N14: 9 | O14: 1492.2047 | P14: R&R | Q14: 8
A15: Position | D15: No. | E15: Hours | F15: Rate/hour | G15: Amount | N15: 10 | O15: 1743.0888 | P15: R&R
A16: Foreman | D16: =M29 -> 1 | E16: =P30 -> 5 | F16: =[3]LABOR!C4 -> 98.84 | G16: =ROUND(F16*E16*D16,2) -> 494.2 | J16: =D16*E16 -> 5 | N16: 11 | O16: 1917.0764 | P16: R&R w/ prposed LD.
A17: Mason | D17: =M30 -> 1 | E17: =P29 -> 5 | F17: =[3]LABOR!C6 -> 81.09 | G17: =ROUND(F17*E17*D17,2) -> 405.45 | J17: =D17*E17 -> 5 | N17: 12 | O17: 1933.234 | P17: R&R
A18: Carpenter/Steelman | D18: =M31 -> 1 | E18: =P31 -> 5 | F18: =F17 -> 81.09 | G18: =ROUND(F18*E18*D18,2) -> 405.45 | J18: =D18*E18 -> 5 | N18: 13 | O18: 2020.8597 | P18: R&R
F19: Skilled Sub-Total | G19: =ROUND(SUM(G16:G18),2) -> 1305.1 | J19: =D19*E19 -> 0 | N19: 14 | O19: 2169.4439 | P19: R&R
A20: Laborer | D20: =M32 -> 4 | E20: =P32 -> 5 | F20: =[3]LABOR!C7 -> 62.38 | G20: =ROUND(F20*E20*D20,2) -> 1247.6 | J20: =D20*E20 -> 20 | O20: Total | Q20: =Q6*10 -> 70
F21: Unskilled Sub-Total | G21: =ROUND(G20,2) -> 1247.6 | J21: =D21*E21 -> 0 | Q21: =Q13*2 -> 16
F22: 1.b. Total Labor Cost = | G22: =ROUND(G19+G21,2) -> 2552.7 | J22: =SUM(J16:J21) -> 35 | Q22: =SUM(Q20:Q21) -> 86
A24: 1.c. | B24: Equipment Rental (Operated)
A25: Make, Model & Capacity of Equipment | D25: No. | E25: Hours | F25: Rate/hour | G25: Amount | K25: Manpower/ Equipment | M25: No. | N25: Quantities | O25: ( Output/Hour ) | P25: Duration
A26: Backhoe, 0.80 cu.m.) | D26: =M27 -> 1 | E26: =P27 -> 2.5 | F26: ='[3]ACEL 2014'!F21 -> 1537 | G26: =D26*E26*F26 -> 3842.5 | M26: of Unit | N26: l.m. | P26: ( hours )
A27: Plate Compactor (5Hp) | D27: =M27 -> 1 | E27: =P27 -> 2.5 | F27: ='[3]ACEL 2014'!F15 -> 123 | G27: =ROUND(F27*E27*D27,2) -> 307.5 | K27: Backhoe | M27: 1 | P27: =P30/2 -> 2.5
A28: Minor Tools (10% of Labor) | F28: =ROUND(G22*0.1,2) -> 255.27 | G28: =F28 -> 255.27 | K28: Plate Compactor | M28: 1 | P28: =P30/2 -> 2.5
F29: 1.c. Total Equipment Rental Cost = | G29: =ROUND(SUM(G26:G28),2) -> 4405.27 | K29: Foreman | M29: 1 | P29: =P30 -> 5
K30: Mason | M30: 1 | N30: =G3 -> 9 | O30: =1.75 -> 1.75 | P30: =ROUND(N30/O30,0) -> 5
F31: 1. Total Direct Cost (1a+1b+1c) = | G31: =ROUND(G12+G22+G29,2) -> 20255.33 | K31: Carpenter/Steelman | M31: 1 | P31: =P30 -> 5
A32: 2. INDIRECT COST | K32: Laborer | M32: 4 | P32: =P30 -> 5
A33: Description | F33: % | G33: Amount | O33: No. of Days = | P33: =P29/8 -> 0.625
A34: 2.a. | B34: Overhead, Contingencies, and Misc. Expenses (OCM) | F34: 0.1 | G34: =ROUND(G31*F34,2) -> 2025.53
A35: 2.b. | B35: Contractor's Profit (CP) | F35: 0.08 | G35: =ROUND(G31*F35,2) -> 1620.43
A36: 2.c. | B36: Contractor's Tax (CT) | F36: 0.05 | G36: =ROUND((G35+G34+G31)*F36,2) -> 1195.06
F38: 2. Total Indirect Cost (2a+2b+2c) = | G38: =ROUND(SUM(G34:G36),2) -> 4841.02
A40: A. | B40: Total Item Cost (1+2) | G40: =ROUND(G31+G38,2) -> 25096.35
A41: B. | B41: Total Quantity of Item of Work | G41: =G3 -> 9
A42: C. | B42: Unit | G42: =G2 -> ln.m.
A43: D. | B43: Item Unit Cost (A / B) | G43: =ROUND(G40/G41,2) -> 2788.48
E44: Adjusted Item Cost | G44: =G43*G41 -> 25096.32
